alu.vhdl
library ieee;
use ieee.std_logic_1164.all;
use IEEE.numeric_std.all;

entity alu is
port(	A:	in std_logic_vector (7 downto 0);
        B:	in std_logic_vector (7 downto 0);
		opField: in std_logic_vector (1 downto 0); --This corresponds to the opfield in the 8-bit ISA instruction
		O:	out std_logic_vector(7 downto 0);
        EQ: out std_logic
);
end alu;

architecture behav of alu is
signal temp: std_logic_vector(1 downto 0);
signal sum: std_logic_vector(7 downto 0);
begin
process(A, B, opField, temp, sum) is
begin
    temp(1) <= opField(1) xor opField(0);
    temp(0) <= (opField(1) and opField(0)) or (opField(1) and not opField(0));

    EQ <= '0';
	if(temp = "00") then
        sum <= std_logic_vector(signed(A) + signed(B));
        O <= sum;
    elsif(temp = "01") then
        sum <= std_logic_vector(signed(A) + signed(not B) + 1); --two's complement subtraction
        O <= sum;
    elsif(temp = "10") then
    else
        if(A = B) then
            EQ <= '1';
        else  
            EQ <= '0';
        end if;
    end if;
end process;
end behav;

alu_tb.vhdl
library ieee;
use ieee.std_logic_1164.all;

--  A testbench has no ports.
entity alu_tb is
end alu_tb;

architecture behav of alu_tb is
--  Declaration of the component that will be instantiated.
component alu
port(	A:	in std_logic_vector (7 downto 0);
        B:	in std_logic_vector (7 downto 0);
		opField: in std_logic_vector (1 downto 0); --This corresponds to the opfield of the 8-bit ISA instruction
		O:	out std_logic_vector(7 downto 0);
        EQ: out std_logic
);
end component;
--  Specifies which entity is bound with the component.
signal a, b, o : std_logic_vector(7 downto 0);
signal op : std_logic_vector(1 downto 0);
signal eq : std_logic;
begin
--  Component instantiation.
alu1: alu port map (A => a, B => b, opField => op, O => o, EQ => eq);

--  This process does the real job.
process
type pattern_type is record
--  The inputs of the shift_reg.
a, b, o: std_logic_vector (7 downto 0);
op: std_logic_vector(1 downto 0);
eq: std_logic;
end record;
--  The patterns to apply.
type pattern_array is array (natural range <>) of pattern_type;
constant patterns : pattern_array := -- Order goes: Upper, Lower, Output, Overflow, Underflow, Select
(("10000001", "00000011", "10000100", "00", '0'), --test -127 + 3 = -124
("00000001", "00000001", "00000010", "00", '0'), --test 1 + 1 = 2
("00000011", "00000001", "00000010", "01", '0'), --test do nothing (notice how O output doesn't change)
("00010000", "00000001", "00000010", "01", '0'), --test do nothing (notice how O output doesn't change)
("11111111", "00000001", "00000010", "10", '0'), --test false equal (notice how O output doesn't change)
("11110000", "11110000", "00000010", "10", '1'), --test true equal (notice how O output doesn't change)
("00000011", "10000001", "10000100", "00", '0'), --test 3 + -127 = -124
("00010000", "11111101", "00010011", "11", '0'), --test 16 - (-3) = 19
("00000001", "00000001", "00000000", "11", '0')); --test 1 - 1 = 0
begin
--  Check each pattern.
for n in patterns'range loop
--  Set the inputs.
a <= patterns(n).a;
b <= patterns(n).b;
op <= patterns(n).op;
--  Wait for the results.
wait for 1 ns;
--  Check the outputs.
assert o = patterns(n).o
report "bad output value" severity error;
assert eq = patterns(n).eq
report "bad eq value" severity error;
end loop;
assert false report "end of test" severity note;
--  Wait forever; this will finish the simulation.
wait;
end process;
end behav;

=alu_tb.vcd
$date
  Sun May  9 12:59:30 2021
$end
$version
  GHDL v0
$end
$timescale
  1 fs
$end
$scope module standard $end
$upscope $end
$scope module std_logic_1164 $end
$upscope $end
$scope module numeric_std $end
$upscope $end
$scope module alu_tb $end
$var reg 8 ! a[7:0] $end
$var reg 8 " b[7:0] $end
$var reg 8 # o[7:0] $end
$var reg 2 $ op[1:0] $end
$var reg 1 % eq $end
$scope module alu1 $end
$var reg 8 & a[7:0] $end
$var reg 8 ' b[7:0] $end
$var reg 2 ( opfield[1:0] $end
$var reg 8 ) o[7:0] $end
$var reg 1 * eq $end
$var reg 2 + temp[1:0] $end
$var reg 8 , sum[7:0] $end
$upscope $end
$upscope $end
$enddefinitions $end
#0
b10000001 !
b00000011 "
b10000100 #
b00 $
0%
b10000001 &
b00000011 '
b00 (
b10000100 )
0*
b00 +
b10000100 ,
#1000000
b00000001 !
b00000001 "
b00000010 #
b00000001 &
b00000001 '
b00000010 )
b00000010 ,
#2000000
b00000011 !
b01 $
b00000011 &
b01 (
b10 +
b00000100 ,
#3000000
b00010000 !
b00010000 &
#4000000
b11111111 !
b10 $
b11111111 &
b10 (
b11 +
#5000000
b11110000 !
b11110000 "
1%
b11110000 &
b11110000 '
1*
#6000000
b00000011 !
b10000001 "
b10000100 #
b00 $
0%
b00000011 &
b10000001 '
b00 (
b10000100 )
0*
b00 +
b10000100 ,
#7000000
b00010000 !
b11111101 "
b00010011 #
b11 $
b00010000 &
b11111101 '
b11 (
b00010011 )
b01 +
b00010011 ,
#8000000
b00000001 !
b00000001 "
b00000000 #
b00000001 &
b00000001 '
b00000000 )
b00000000 ,
