alu.vhdl
library ieee;
use ieee.std_logic_1164.all;
use IEEE.numeric_std.all;

entity alu is
port(	A:	in std_logic_vector (7 downto 0):= "00000000";
        B:	in std_logic_vector (7 downto 0):= "00000000";
		opField: in std_logic_vector (1 downto 0); --This corresponds to the opfield in the 8-bit ISA instruction
		O:	out std_logic_vector(7 downto 0) := "00000000";
        EQ: out std_logic
);
end alu;

architecture behav of alu is
signal temp: std_logic_vector(1 downto 0);
signal sum: std_logic_vector(7 downto 0);
begin
process(A, B, opField, temp, sum) is
begin
    temp(1) <= opField(1) xor opField(0);
    temp(0) <= (opField(1) and opField(0)) or (opField(1) and not opField(0));

    EQ <= '0';
	if(temp = "00") then
        sum <= std_logic_vector(signed(A) + signed(B));
        O <= sum;
    elsif(temp = "01") then
        sum <= std_logic_vector(signed(A) + signed(not B) + 1); --two's complement subtraction
        O <= sum;
    elsif(temp = "10") then
    else
        if(A = B) then
            EQ <= '1';
        else  
            EQ <= '0';
        end if;
    end if;
end process;
end behav;

register.vhdl
library ieee;
use ieee.std_logic_1164.all;

entity reg is
port(	I:	in std_logic_vector (7 downto 0);
		clk:	in std_logic;
		O:	out std_logic_vector(7 downto 0)
);
end reg;

architecture behav of reg is
begin
process(clk) is
begin
	if(clk='1' and clk'event) then
		O <= I;
	end if;
end process;
end behav;

registerFile.vhdl
library ieee;
use ieee.std_logic_1164.all;

entity registerFile is
port(	rs1:	in std_logic_vector (1 downto 0); -- for loading addresses: 00 = register 1, 01 = register 2, 10 = register 3, 11 = register 4
		rs2: in std_logic_vector (1 downto 0); -- for loading addresses
		clk:    in std_logic;
        ws:        in std_logic_vector(1 downto 0); -- write selects address: 00 = register 1, 01 = register 2, 10 = register 3, 11 = register 4
		wd:		in std_logic_vector(7 downto 0); -- write data
        we:		in std_logic; -- positive level triggering in problem 3
		rd1:		out std_logic_vector (7 downto 0) := "00000000"; -- 0: don't do anything; 1: shift_reg is enabled
        rd2:		out std_logic_vector (7 downto 0) := "00000000" -- 0: don't do anything; 1: shift_reg is enabled
);
end registerFile;


architecture behav of registerFile is

component reg
port (	I:	in std_logic_vector (7 downto 0) := "00000000";
        clk:    in std_logic; 
        O:	out std_logic_vector(7 downto 0) := "00000000"
);
end component;

signal i1: std_logic_vector(7 downto 0) := "00000000";
signal i2: std_logic_vector(7 downto 0) := "00000000";
signal i3: std_logic_vector(7 downto 0) := "00000000";
signal i4: std_logic_vector(7 downto 0) := "00000000";
signal o1: std_logic_vector(7 downto 0) := "00000000";
signal o2: std_logic_vector(7 downto 0) := "00000000";
signal o3: std_logic_vector(7 downto 0) := "00000000";
signal o4: std_logic_vector(7 downto 0) := "00000000";
signal weAndws : std_logic_vector(2 downto 0);
begin

--  Component instantiation.
reg_1: reg port map ( I => i1, clk => clk, O => o1); --left 4 bits
reg_2: reg port map ( I => i2, clk => clk, O => o2); --right 4 bits
reg_3: reg port map ( I => i3, clk => clk, O => o3); --right 4 bits
reg_4: reg port map ( I => i4, clk => clk, O => o4); --right 4 bits

weAndws <= we & ws;

with weAndws select
    i1 <=   wd when "100",
            o1 when others;

with weAndws select
i2 <=   wd when "101",
        o2 when others;     

with weAndws select
i3 <=   wd when "110",
        o3 when others;

with weAndws select
i4 <=   wd when "111",
    o4 when others;  

with rs1 select --combinational read of rs1
    rd1 <= o1 when "00",
           o2 when "01",
           o3 when "10",
           o4 when others;

with rs2 select --combinational read of rs2
    rd2 <= o1 when "00",
           o2 when "01",
           o3 when "10",
           o4 when others;

end behav;

calculator.vhdl
library ieee;
use ieee.std_logic_1164.all;
use IEEE.numeric_std.all;

entity calculator is 
    port( --opcode key: ADD = 00, SUB = 11, LOAD = 01, CMP/PRINT = 10
        I: in std_logic_vector(7 downto 0) := "00000000"; --format is: opcode (7 downto 6), rs (5 downto 4), rt (3 downto 2), rd (1 downto 0) for rType, 
        clk: in std_logic                                 --opcode(7 downto 6), rd(5 downto 4), im (3 downto 0) for I-type
    );
end entity calculator;

architecture behavioral of calculator is
component alu is  --this is the alu need to add 1 because vhdl name
    port(	A:	in std_logic_vector (7 downto 0);
        B:	in std_logic_vector (7 downto 0);
		opField: in std_logic_vector (1 downto 0); --This corresponds to the opfield in the 8-bit ISA instruction
		O:	out std_logic_vector(7 downto 0);
        EQ: out std_logic
);
end component alu;

component registerFile is
    port(	rs1:	in std_logic_vector (1 downto 0); -- for loading addresses: 00 = register 1, 01 = register 2, 10 = register 3, 11 = register 4
		rs2: in std_logic_vector (1 downto 0); -- for loading addresses
		clk:    in std_logic;
        ws:        in std_logic_vector(1 downto 0); -- write selects address: 00 = register 1, 01 = register 2, 10 = register 3, 11 = register 4
		wd:		in std_logic_vector(7 downto 0); -- write data
        we:		in std_logic; -- positive level triggering in problem 3
		rd1:		out std_logic_vector (7 downto 0); -- 0: don't do anything; 1: shift_reg is enabled
        rd2:		out std_logic_vector (7 downto 0) -- 0: don't do anything; 1: shift_reg is enabled
);
end component registerFile;

signal regOut1, regOut2, regOut3, regOut4: std_logic_vector(7 downto 0);
signal we_signal : std_logic :='0'; --write enable = 1 for all except branch/compare
signal regIn1, regIn2, ws_signal :std_logic_vector(1 downto 0);


signal immediateOutput : std_logic_vector(7 downto 0) := "00000000";


signal regFileInputA, regFileInputB, regDest: std_logic_vector(1 downto 0);
signal regWrite : std_logic_vector(7 downto 0);
signal writeEnable : std_logic;
signal regFileOutputA, regFileOutputB: std_logic_vector(7 downto 0);
signal aluInputA, aluInputB: std_logic_vector(7 downto 0);
signal aluOpField: std_logic_vector(1 downto 0);
signal aluOutput, aluOutputBuffer : std_logic_vector(7 downto 0);
signal aluBranch: std_logic;
signal rType : std_logic; --signifies whether it is add/subtract (1) or load (0)
signal immExtend : std_logic_vector(7 downto 0); --immedate 0 or 1 padded
signal opCodeAndClk: std_logic_vector(2 downto 0);

--signal ws_signal : std_logic_vector (1 downto 0) := "00";
begin  
    regFile : registerFile port map(rs1 => regFileInputA, rs2 => regFileInputB, clk => clk, ws => regDest, wd=>regWrite, we => writeEnable,rd1 =>regFileOutputA, rd2 =>regFileOutputB  );
    alu1: alu port map(A => aluInputA, B => aluInputB, opField => aluOpField, O => aluOutput, EQ => aluBranch);

    with I(7 downto 6) select 
        rType <= '0' when "01", --load is i type
                 '0' when "10", --print i guess
                 '1' when others;
    
    with rType select
        regDest <= I(1 downto 0) when '1', --add/sub has regDest at last 2 bits
                   I(5 downto 4) when others; --load is at 2 bits 2 to the left 
    
    regFileInputA <= I(5 downto 4);

    with rType select
        regFileInputB <= I(3 downto 2) when '1', --add/sub format
                         I(5 downto 4) when others; --just to have an expected return value, the registerFile will select rd as its A and B input on load

    with rType select
        regWrite <= aluOutput when '1', --add/sub gets regWrite from alu
                    immExtend when others;
    
    with I(3) select
        immExtend <= "0000" & I(3 downto 0) when '0',
                     "1111" & I(3 downto 0) when others;

    aluOpField <= I(7 downto 6);

    aluInputA <= regFileOutputA;
    aluInputB <= regFileOutputB;

    with I(7 downto 6) select 
        writeEnable <= '1' when "00",
                       '1' when "11",
                       '1' when "01",
                       '0' when others;
    
    opCodeAndClk <= I(7 downto 6) & clk;
    
    process(clk)
    begin
        if(clk = '1') then
            report "regWrite: " & integer'image(to_integer(signed(RegWrite))); 
        end if;
    end process;

end architecture behavioral;

calculator_tb.vhdl
library ieee;
use ieee.std_logic_1164.all;

--  A testbench has no ports.
entity calculator_tb is
end calculator_tb;

architecture behav of calculator_tb is
--  Declaration of the component that will be instantiated.
component calculator
port(	I: in std_logic_vector(7 downto 0);
        clk: in std_logic
);
end component;
--  Specifies which entity is bound with the component.
signal i: std_logic_vector(7 downto 0);
signal clock: std_logic;
begin
--  Component instantiation.
calculator1 : calculator port map(I => I, clk => clock);

--  This process does the real job.
process
type pattern_type is record
--  The inputs of the shift_reg.
i: std_logic_vector(7 downto 0);
clock: std_logic;
end record;
--  The patterns to apply.
type pattern_array is array (natural range <>) of pattern_type; --let clock period = 4ns
constant patterns : pattern_array := -- Order goes: Input address rs1,rs2,ws ; input data rd1,rd2,wd ; we clk
(
("01000101", '0'), --nothing happens on falling edge
("01000010", '0'),
("01000010", '1'), --set r1 to 0010
("01000111", '1'), --can't edit registers on falling edge
("01000111", '0'),
("00000000", '0'),
("00000000", '1'), --add r1 and r1 to r1 (0010 + 0010 = 0100)
("01011010", '1'), --instruction at non-rising edge will be buffered to next clock cycle (if instruction is held)
("01011010", '0'),
("01011010", '0'),
("01011010", '1'), --set r2 to 1010
("01000111", '1'),
("00000000", '0'), --rapid changes when clock = 0 has no effect
("01100001", '0'),
("01100001", '1'), --set r3 to 0001
("01100001", '1'),
("00001001", '0'), 
("00001001", '0'),
("00001001", '1'), --add r1 and r3 and put it in r2 (0100 + 0001 = 0101)
("01000011", '1'),
("01000011", '0'),
("01110111", '0'),
("01110111", '1'), --set r4 to 0111
("01101011", '1')); 
begin
--  Check each pattern.
for n in patterns'range loop
--  Set the inputs.
i <= patterns(n).i;
clock <= patterns(n).clock;

--  Wait for the results.
wait for 1 ns;
--  Check the outputs.
end loop;
assert false report "end of test" severity note;
--  Wait forever; this will finish the simulation.
wait;
end process;
end behav;

calculator.vcd
$date
  Fri May 21 20:25:48 2021
$end
$version
  GHDL v0
$end
$timescale
  1 fs
$end
$scope module standard $end
$upscope $end
$scope module std_logic_1164 $end
$upscope $end
$scope module numeric_std $end
$upscope $end
$scope module calculator_tb $end
$var reg 8 ! i[7:0] $end
$var reg 1 " clock $end
$scope module calculator1 $end
$var reg 8 # i[7:0] $end
$var reg 1 $ clk $end
$var reg 8 % regout1[7:0] $end
$var reg 8 & regout2[7:0] $end
$var reg 8 ' regout3[7:0] $end
$var reg 8 ( regout4[7:0] $end
$var reg 1 ) we_signal $end
$var reg 2 * regin1[1:0] $end
$var reg 2 + regin2[1:0] $end
$var reg 2 , ws_signal[1:0] $end
$var reg 8 - immediateoutput[7:0] $end
$var reg 2 . regfileinputa[1:0] $end
$var reg 2 / regfileinputb[1:0] $end
$var reg 2 0 regdest[1:0] $end
$var reg 8 1 regwrite[7:0] $end
$var reg 1 2 writeenable $end
$var reg 8 3 regfileoutputa[7:0] $end
$var reg 8 4 regfileoutputb[7:0] $end
$var reg 8 5 aluinputa[7:0] $end
$var reg 8 6 aluinputb[7:0] $end
$var reg 2 7 aluopfield[1:0] $end
$var reg 8 8 aluoutput[7:0] $end
$var reg 8 9 aluoutputbuffer[7:0] $end
$var reg 1 : alubranch $end
$var reg 1 ; rtype $end
$var reg 8 < immextend[7:0] $end
$var reg 3 = opcodeandclk[2:0] $end
$scope module regfile $end
$var reg 2 > rs1[1:0] $end
$var reg 2 ? rs2[1:0] $end
$var reg 1 @ clk $end
$var reg 2 A ws[1:0] $end
$var reg 8 B wd[7:0] $end
$var reg 1 C we $end
$var reg 8 D rd1[7:0] $end
$var reg 8 E rd2[7:0] $end
$var reg 8 F i1[7:0] $end
$var reg 8 G i2[7:0] $end
$var reg 8 H i3[7:0] $end
$var reg 8 I i4[7:0] $end
$var reg 8 J o1[7:0] $end
$var reg 8 K o2[7:0] $end
$var reg 8 L o3[7:0] $end
$var reg 8 M o4[7:0] $end
$var reg 3 N weandws[2:0] $end
$scope module reg_1 $end
$var reg 8 O i[7:0] $end
$var reg 1 P clk $end
$var reg 8 Q o[7:0] $end
$upscope $end
$scope module reg_2 $end
$var reg 8 R i[7:0] $end
$var reg 1 S clk $end
$var reg 8 T o[7:0] $end
$upscope $end
$scope module reg_3 $end
$var reg 8 U i[7:0] $end
$var reg 1 V clk $end
$var reg 8 W o[7:0] $end
$upscope $end
$scope module reg_4 $end
$var reg 8 X i[7:0] $end
$var reg 1 Y clk $end
$var reg 8 Z o[7:0] $end
$upscope $end
$upscope $end
$scope module alu1 $end
$var reg 8 [ a[7:0] $end
$var reg 8 \ b[7:0] $end
$var reg 2 ] opfield[1:0] $end
$var reg 8 ^ o[7:0] $end
$var reg 1 _ eq $end
$var reg 2 ` temp[1:0] $end
$var reg 8 a sum[7:0] $end
$upscope $end
$upscope $end
$upscope $end
$enddefinitions $end
#0
b01000101 !
0"
b01000101 #
0$
bUUUUUUUU %
bUUUUUUUU &
bUUUUUUUU '
bUUUUUUUU (
0)
bUU *
bUU +
bUU ,
b00000000 -
b00 .
b00 /
b00 0
b00000101 1
12
b00000000 3
b00000000 4
b00000000 5
b00000000 6
b01 7
b00000000 8
bUUUUUUUU 9
0:
0;
b00000101 <
b010 =
b00 >
b00 ?
0@
b00 A
b00000101 B
1C
b00000000 D
b00000000 E
b00000101 F
b00000000 G
b00000000 H
b00000000 I
b00000000 J
b00000000 K
b00000000 L
b00000000 M
b100 N
b00000101 O
0P
b00000000 Q
b00000000 R
0S
b00000000 T
b00000000 U
0V
b00000000 W
b00000000 X
0Y
b00000000 Z
b00000000 [
b00000000 \
b01 ]
b00000000 ^
0_
b10 `
bUUUUUUUU a
#1000000
b01000010 !
b01000010 #
b00000010 1
b00000010 <
b00000010 B
b00000010 F
b00000010 O
#2000000
1"
1$
b00000010 3
b00000010 4
b00000010 5
b00000010 6
b011 =
1@
b00000010 D
b00000010 E
b00000010 J
1P
b00000010 Q
1S
1V
1Y
b00000010 [
b00000010 \
#3000000
b01000111 !
b01000111 #
b00000111 1
b00000111 <
b00000111 B
b00000111 F
b00000111 O
#4000000
0"
0$
b010 =
0@
0P
0S
0V
0Y
#5000000
b00000000 !
b00000000 #
b00000100 1
b00 7
b00000100 8
1;
b00000000 <
b000 =
b00000100 B
b00000100 F
b00000100 O
b00 ]
b00000100 ^
b00 `
b00000100 a
#6000000
1"
1$
b00001000 1
b00000100 3
b00000100 4
b00000100 5
b00000100 6
b00001000 8
b001 =
1@
b00001000 B
b00000100 D
b00000100 E
b00001000 F
b00000100 J
b00001000 O
1P
b00000100 Q
1S
1V
1Y
b00000100 [
b00000100 \
b00001000 ^
b00001000 a
#7000000
b01011010 !
b01011010 #
b01 .
b01 /
b01 0
b11111010 1
b00000000 3
b00000000 4
b00000000 5
b00000000 6
b01 7
0;
b11111010 <
b011 =
b01 >
b01 ?
b01 A
b11111010 B
b00000000 D
b00000000 E
b00000100 F
b11111010 G
b00000000 H
b101 N
b00000100 O
b11111010 R
b00000000 U
b00000000 [
b00000000 \
b01 ]
b10 `
#8000000
0"
0$
b010 =
0@
0P
0S
0V
0Y
#9000000
#10000000
1"
1$
b11111010 3
b11111010 4
b11111010 5
b11111010 6
b011 =
1@
b11111010 D
b11111010 E
b11111010 K
1P
1S
b11111010 T
1V
1Y
b11111010 [
b11111010 \
#11000000
b01000111 !
b01000111 #
b00 .
b00 /
b00 0
b00000111 1
b00000100 3
b00000100 4
b00000100 5
b00000100 6
b00000111 <
b00 >
b00 ?
b00 A
b00000111 B
b00000100 D
b00000100 E
b00000111 F
b100 N
b00000111 O
b00000100 [
b00000100 \
#12000000
b00000000 !
0"
b00000000 #
0$
b00001000 1
b00 7
1;
b00000000 <
b000 =
0@
b00001000 B
b00001000 F
b00001000 O
0P
0S
0V
0Y
b00 ]
b00 `
#13000000
b01100001 !
b01100001 #
b10 .
b10 /
b10 0
b00000001 1
b00000000 3
b00000000 4
b00000000 5
b00000000 6
b01 7
0;
b00000001 <
b010 =
b10 >
b10 ?
b10 A
b00000001 B
b00000000 D
b00000000 E
b00000100 F
b11111010 G
b00000001 H
b110 N
b00000100 O
b11111010 R
b00000001 U
b00000000 [
b00000000 \
b01 ]
b10 `
#14000000
1"
1$
b00000001 3
b00000001 4
b00000001 5
b00000001 6
b011 =
1@
b00000001 D
b00000001 E
b00000001 L
1P
1S
1V
b00000001 W
1Y
b00000001 [
b00000001 \
#15000000
#16000000
b00001001 !
0"
b00001001 #
0$
b00 .
b10 /
b01 0
b00000101 1
b00000100 3
b00000001 4
b00000100 5
b00000001 6
b00 7
b00000101 8
1;
b11111001 <
b000 =
b00 >
b10 ?
0@
b01 A
b00000101 B
b00000100 D
b00000001 E
b00000100 F
b00000101 G
b101 N
b00000100 O
0P
b00000101 R
0S
0V
0Y
b00000100 [
b00000001 \
b00 ]
b00000101 ^
b00 `
b00000101 a
#17000000
#18000000
1"
1$
b001 =
1@
b00000101 K
1P
1S
b00000101 T
1V
1Y
#19000000
b01000011 !
b01000011 #
b00 /
b00 0
b00000011 1
b00000100 4
b00000100 6
b01 7
0;
b00000011 <
b011 =
b00 ?
b00 A
b00000011 B
b00000100 E
b00000011 F
b00000000 I
b100 N
b00000011 O
b00000000 X
b00000100 \
b01 ]
b10 `
#20000000
0"
0$
b010 =
0@
0P
0S
0V
0Y
#21000000
b01110111 !
b01110111 #
b11 .
b11 /
b11 0
b00000111 1
b00000000 3
b00000000 4
b00000000 5
b00000000 6
b00000111 <
b11 >
b11 ?
b11 A
b00000111 B
b00000000 D
b00000000 E
b00000100 F
b00000111 I
b111 N
b00000100 O
b00000111 X
b00000000 [
b00000000 \
#22000000
1"
1$
b00000111 3
b00000111 4
b00000111 5
b00000111 6
b011 =
1@
b00000111 D
b00000111 E
b00000111 M
1P
1S
1V
1Y
b00000111 Z
b00000111 [
b00000111 \
#23000000
b01101011 !
b01101011 #
b10 .
b10 /
b10 0
b11111011 1
b00000001 3
b00000001 4
b00000001 5
b00000001 6
b11111011 <
b10 >
b10 ?
b10 A
b11111011 B
b00000001 D
b00000001 E
b11111011 H
b110 N
b11111011 U
b00000001 [
b00000001 \
