alu.vhdl
library ieee;
use ieee.std_logic_1164.all;
use IEEE.numeric_std.all;

entity alu is
port(	A:	in std_logic_vector (7 downto 0):= "00000000";
        B:	in std_logic_vector (7 downto 0):= "00000000";
		opField: in std_logic_vector (1 downto 0); --This corresponds to the opfield in the 8-bit ISA instruction
		O:	out std_logic_vector(7 downto 0) := "00000000";
        EQ: out std_logic
);
end alu;

architecture behav of alu is
signal temp: std_logic_vector(1 downto 0);
signal sum: std_logic_vector(7 downto 0);
begin
process(A, B, opField, temp, sum) is
begin
    temp(1) <= opField(1) xor opField(0);
    temp(0) <= (opField(1) and opField(0)) or (opField(1) and not opField(0));

    EQ <= '0';
	if(temp = "00") then
        sum <= std_logic_vector(signed(A) + signed(B));
        O <= sum;
    elsif(temp = "01") then
        sum <= std_logic_vector(signed(A) + signed(not B) + 1); --two's complement subtraction
        O <= sum;
    elsif(temp = "10") then
    else
        if(A = B) then
            EQ <= '1';
        else  
            EQ <= '0';
        end if;
    end if;
end process;
end behav;

register.vhdl
library ieee;
use ieee.std_logic_1164.all;

entity reg is
port(	I:	in std_logic_vector (7 downto 0);
		clk:	in std_logic;
		O:	out std_logic_vector(7 downto 0)
);
end reg;

architecture behav of reg is
begin
process(clk) is
begin
	if(clk='1' and clk'event) then
		O <= I;
	end if;
end process;
end behav;

registerFile.vhdl
library ieee;
use ieee.std_logic_1164.all;

entity registerFile is
port(	rs1:	in std_logic_vector (1 downto 0); -- for loading addresses: 00 = register 1, 01 = register 2, 10 = register 3, 11 = register 4
		rs2: in std_logic_vector (1 downto 0); -- for loading addresses
		clk:    in std_logic;
        ws:        in std_logic_vector(1 downto 0); -- write selects address: 00 = register 1, 01 = register 2, 10 = register 3, 11 = register 4
		wd:		in std_logic_vector(7 downto 0); -- write data
        we:		in std_logic; -- positive level triggering in problem 3
		rd1:		out std_logic_vector (7 downto 0) := "00000000"; -- 0: don't do anything; 1: shift_reg is enabled
        rd2:		out std_logic_vector (7 downto 0) := "00000000" -- 0: don't do anything; 1: shift_reg is enabled
);
end registerFile;


architecture behav of registerFile is

component reg
port (	I:	in std_logic_vector (7 downto 0) := "00000000";
        clk:    in std_logic; 
        O:	out std_logic_vector(7 downto 0) := "00000000"
);
end component;

signal i1: std_logic_vector(7 downto 0) := "00000000";
signal i2: std_logic_vector(7 downto 0) := "00000000";
signal i3: std_logic_vector(7 downto 0) := "00000000";
signal i4: std_logic_vector(7 downto 0) := "00000000";
signal o1: std_logic_vector(7 downto 0) := "00000000";
signal o2: std_logic_vector(7 downto 0) := "00000000";
signal o3: std_logic_vector(7 downto 0) := "00000000";
signal o4: std_logic_vector(7 downto 0) := "00000000";
signal weAndws : std_logic_vector(2 downto 0);
signal clk_sig1, clk_sig2, clk_sig3 : std_logic;
begin

--  Component instantiation.
reg_1: reg port map ( I => i1, clk => clk_sig3, O => o1); --left 4 bits
reg_2: reg port map ( I => i2, clk => clk_sig3, O => o2); --right 4 bits
reg_3: reg port map ( I => i3, clk => clk_sig3, O => o3); --right 4 bits
reg_4: reg port map ( I => i4, clk => clk_sig3, O => o4); --right 4 bits

weAndws <= we & ws;

with weAndws select
    i1 <=   wd when "100",
            o1 when others;

with weAndws select
i2 <=   wd when "101",
        o2 when others;     

with weAndws select
i3 <=   wd when "110",
        o3 when others;

with weAndws select
i4 <=   wd when "111",
    o4 when others;  

with rs1 select --combinational read of rs1
    rd1 <= o1 when "00",
           o2 when "01",
           o3 when "10",
           o4 when others;

with rs2 select --combinational read of rs2
    rd2 <= o1 when "00",
           o2 when "01",
           o3 when "10",
           o4 when others;

process(clk)
begin
    clk_sig1 <= clk;
end process;

process(clk_sig1)
begin
    clk_sig2 <= clk_sig1;
end process;

process(clk_sig2)
begin
    clk_sig3 <= clk_sig2;
end process;

end behav;

calculator.vhdl
library ieee;
use ieee.std_logic_1164.all;
use IEEE.numeric_std.all;

--Things to add:
--Print command (10 same as beq) only time something gets displayed
--beq simply makes nothing get transmitted to registerFile, and nothing gets printed either
--We can make nothing get transmitted to registerFile by making a second signal
--for the inputs of registerFile and muxing that with itself and the updated instructions
--the select is a skip_signal which gets determined by the alu EQ output
--Print statement: opcode == 10, rs == what's getting printed, rt == not used, rd MUST EQUAL 3, OR ELSE IT'S A BEQ

entity calculator is 
    port( --opcode key: ADD = 00, SUB = 11, LOAD = 01, CMP/PRINT = 10
        I: in std_logic_vector(7 downto 0) := "00000000"; --format is: opcode (7 downto 6), rs (5 downto 4), rt (3 downto 2), rd (1 downto 0) for rType, 
        clk: in std_logic                                 --opcode(7 downto 6), rd(5 downto 4), im (3 downto 0) for I-type
    );
end entity calculator;

architecture behavioral of calculator is
component alu is  --this is the alu need to add 1 because vhdl name
    port(	A:	in std_logic_vector (7 downto 0);
        B:	in std_logic_vector (7 downto 0);
		opField: in std_logic_vector (1 downto 0); --This corresponds to the opfield in the 8-bit ISA instruction
		O:	out std_logic_vector(7 downto 0);
        EQ: out std_logic
);
end component alu;

component registerFile is
    port(	rs1:	in std_logic_vector (1 downto 0); -- for loading addresses: 00 = register 1, 01 = register 2, 10 = register 3, 11 = register 4
		rs2: in std_logic_vector (1 downto 0); -- for loading addresses
		clk:    in std_logic;
        ws:        in std_logic_vector(1 downto 0); -- write selects address: 00 = register 1, 01 = register 2, 10 = register 3, 11 = register 4
		wd:		in std_logic_vector(7 downto 0); -- write data
        we:		in std_logic; -- positive level triggering in problem 3
		rd1:		out std_logic_vector (7 downto 0); -- 0: don't do anything; 1: shift_reg is enabled
        rd2:		out std_logic_vector (7 downto 0) -- 0: don't do anything; 1: shift_reg is enabled
);
end component registerFile;

signal regOut1, regOut2, regOut3, regOut4: std_logic_vector(7 downto 0);
signal we_signal : std_logic :='0'; --write enable = 1 for all except branch/compare
signal regIn1, regIn2, ws_signal :std_logic_vector(1 downto 0);


signal immediateOutput : std_logic_vector(7 downto 0) := "00000000";


signal regFileInputA, regFileInputB, regDest: std_logic_vector(1 downto 0);
signal regWrite : std_logic_vector(7 downto 0);
signal writeEnable : std_logic;
signal regFileOutputA, regFileOutputB: std_logic_vector(7 downto 0);
signal aluInputA, aluInputB: std_logic_vector(7 downto 0);
signal aluOpField: std_logic_vector(1 downto 0);
signal aluOutput, aluOutputBuffer : std_logic_vector(7 downto 0);
signal aluBranch: std_logic;
signal rType : std_logic; --signifies whether it is add/subtract (1) or load (0)
signal immExtend : std_logic_vector(7 downto 0); --immedate 0 or 1 padded
signal opCodeAndClk: std_logic_vector(2 downto 0);
signal clk_sig1, clk_sig2, clk_sig3, clk_sig4, clk_sig5, clk_sig6, clk_sig7, clk_sig8, clk_sig9 : std_logic := '0';
signal printOrBranch, printing : std_logic := '0';
signal rTypeAndPrinting : std_logic_vector(1 downto 0);

--signal ws_signal : std_logic_vector (1 downto 0) := "00";
begin  
    regFile : registerFile port map(rs1 => regFileInputA, rs2 => regFileInputB, clk => clk_sig9, ws => regDest, wd=>regWrite, we => writeEnable,rd1 =>regFileOutputA, rd2 =>regFileOutputB  );
    alu1: alu port map(A => aluInputA, B => aluInputB, opField => aluOpField, O => aluOutput, EQ => aluBranch);

    with I(7 downto 6) select 
        rType <= '0' when "01", --load is i type
                 '0' when "10", --print i guess
                 '1' when others;
    
    with rType select
        regDest <= I(1 downto 0) when '1', --add/sub has regDest at last 2 bits
                   I(5 downto 4) when others; --load is at 2 bits 2 to the left 
    
    regFileInputA <= I(5 downto 4);

    with rType select
        regFileInputB <= I(3 downto 2) when '1', --add/sub format
                         I(5 downto 4) when others; --just to have an expected return value, the registerFile will select rd as its A and B input on load

    with I(7 downto 6) select
        printOrBranch <= '1' when "10",
                         '0' when others;
    
    with I(1 downto 0) select
        printing <= printOrBranch when "11",
                    '0' when others;

    rTypeAndPrinting <= rType & printing;
    
    with rTypeAndPrinting select
        regWrite <= aluOutput when "10", --add/sub gets regWrite from alu
                    immExtend when "00", --load gets regWrite from immediate field
                    regFileOutputA when others; --DO NOT CHANGE regWrite WHEN PRINTING = 1
    
    with I(3) select
        immExtend <= "0000" & I(3 downto 0) when '0',
                     "1111" & I(3 downto 0) when others;

    aluOpField <= I(7 downto 6);

    aluInputA <= regFileOutputA;
    aluInputB <= regFileOutputB;

    with I(7 downto 6) select 
        writeEnable <= '1' when "00",
                       '1' when "11",
                       '1' when "01",
                       '0' when others;
    
    opCodeAndClk <= I(7 downto 6) & clk;


    process(clk)
    begin
        if(clk = '1' and clk'event and printing = '1') then
            report integer'image(to_integer(signed(RegWrite))); 
        end if;
        clk_sig1 <= clk;
    end process;

    process(clk_sig1)
    begin
        clk_sig2 <= clk_sig1;
    end process;

    process(clk_sig2)
    begin
        clk_sig3 <= clk_sig2;
    end process;

    process(clk_sig3)
    begin
        clk_sig4 <= clk_sig3;
    end process;

    process(clk_sig4)
    begin
        clk_sig5 <= clk_sig4;
    end process;

    process(clk_sig5)
    begin
        clk_sig6 <= clk_sig5;
    end process;

    process(clk_sig6)
    begin
        clk_sig7 <= clk_sig6;
    end process;

    process(clk_sig7)
    begin
        clk_sig8 <= clk_sig7;
    end process;

    process(clk_sig8)
    begin
        if(clk_sig8 = '1' and clk_sig8'event) then
            --report "regWrite: " & integer'image(to_integer(signed(RegWrite))); --debugging for regWrite
        end if;
        clk_sig9 <= clk_sig8;
    end process;

end architecture behavioral;

calculator_tb.vhdl
library ieee;
use ieee.std_logic_1164.all;
use std.textio.all;

--  A testbench has no ports.
entity calculator_tb is
end calculator_tb;

architecture behav of calculator_tb is
--  Declaration of the component that will be instantiated.
component calculator
port(	I: in std_logic_vector(7 downto 0);
        clk: in std_logic
);
end component;
--  Specifies which entity is bound with the component.
signal I: std_logic_vector(7 downto 0);
signal clock: std_logic;
begin
--  Component instantiation.
calculator1 : calculator port map(I => I, clk => clock);

--  This process does the real job.
--The instructionFile located at instructions.txt contains the instructions:
--01000010   set reg1 to 2
--00000000   set reg1 to reg1 + reg1 (2 + 2 = 4)
--01110100   set reg4 to 4
--10000111   print reg1 (4)
--10000010   skip 2 lines if reg1 == reg4 (true) (4 = 4)
--10000011   print reg1 (4) (skipped)
--01000011   set reg1 to 3 (skipped)
--10001001   skip 1 line if reg1 == reg3 (false) (4 != 0)
--10010011   print reg2 (0)
--01101010   set reg3 to -6
--00101010   add reg3 to reg3 and put in reg3 (-6 + (-6) = -12)
--11001001   subtract reg3 from reg1 and put in reg1 (4 - (-12) = 16)
--10100011   print reg3 (-12)
--10010011   print reg1 (16)
process
      file instructionFile : text is in "instructions.txt"; --Instructions in text(ASCII) file.
      variable vector : bit_vector(7 downto 0);
      variable lineNum : line;
    begin
      while (not(endfile(instructionFile))) loop --Loop to the end of the text file.
        clock <= '0';
        readline(instructionFile, lineNum); --Read instruction from file
        read(lineNum, vector); --Change to bit vector
        I <= to_stdlogicvector(vector); --change bitvector to std_logic_vector
        wait for 1 ns;
        clock <= '1';
        wait for 1 ns;
      end loop;
      wait;
    end process;
    end behav;

calculator.vcd
$date
  Sun May 23 18:02:45 2021
$end
$version
  GHDL v0
$end
$timescale
  1 fs
$end
$scope module standard $end
$upscope $end
$scope module std_logic_1164 $end
$upscope $end
$scope module textio $end
$upscope $end
$scope module numeric_std $end
$upscope $end
$scope module calculator_tb $end
$var reg 8 ! i[7:0] $end
$var reg 1 " clock $end
$scope module calculator1 $end
$var reg 8 # i[7:0] $end
$var reg 1 $ clk $end
$var reg 8 % regout1[7:0] $end
$var reg 8 & regout2[7:0] $end
$var reg 8 ' regout3[7:0] $end
$var reg 8 ( regout4[7:0] $end
$var reg 1 ) we_signal $end
$var reg 2 * regin1[1:0] $end
$var reg 2 + regin2[1:0] $end
$var reg 2 , ws_signal[1:0] $end
$var reg 8 - immediateoutput[7:0] $end
$var reg 2 . regfileinputa[1:0] $end
$var reg 2 / regfileinputb[1:0] $end
$var reg 2 0 regdest[1:0] $end
$var reg 8 1 regwrite[7:0] $end
$var reg 1 2 writeenable $end
$var reg 8 3 regfileoutputa[7:0] $end
$var reg 8 4 regfileoutputb[7:0] $end
$var reg 8 5 aluinputa[7:0] $end
$var reg 8 6 aluinputb[7:0] $end
$var reg 2 7 aluopfield[1:0] $end
$var reg 8 8 aluoutput[7:0] $end
$var reg 8 9 aluoutputbuffer[7:0] $end
$var reg 1 : alubranch $end
$var reg 1 ; rtype $end
$var reg 8 < immextend[7:0] $end
$var reg 3 = opcodeandclk[2:0] $end
$var reg 1 > clk_sig1 $end
$var reg 1 ? clk_sig2 $end
$var reg 1 @ clk_sig3 $end
$var reg 1 A clk_sig4 $end
$var reg 1 B clk_sig5 $end
$var reg 1 C clk_sig6 $end
$var reg 1 D clk_sig7 $end
$var reg 1 E clk_sig8 $end
$var reg 1 F clk_sig9 $end
$var reg 1 G printorbranch $end
$var reg 1 H printing $end
$var reg 2 I rtypeandprinting[1:0] $end
$scope module regfile $end
$var reg 2 J rs1[1:0] $end
$var reg 2 K rs2[1:0] $end
$var reg 1 L clk $end
$var reg 2 M ws[1:0] $end
$var reg 8 N wd[7:0] $end
$var reg 1 O we $end
$var reg 8 P rd1[7:0] $end
$var reg 8 Q rd2[7:0] $end
$var reg 8 R i1[7:0] $end
$var reg 8 S i2[7:0] $end
$var reg 8 T i3[7:0] $end
$var reg 8 U i4[7:0] $end
$var reg 8 V o1[7:0] $end
$var reg 8 W o2[7:0] $end
$var reg 8 X o3[7:0] $end
$var reg 8 Y o4[7:0] $end
$var reg 3 Z weandws[2:0] $end
$var reg 1 [ clk_sig1 $end
$var reg 1 \ clk_sig2 $end
$var reg 1 ] clk_sig3 $end
$scope module reg_1 $end
$var reg 8 ^ i[7:0] $end
$var reg 1 _ clk $end
$var reg 8 ` o[7:0] $end
$upscope $end
$scope module reg_2 $end
$var reg 8 a i[7:0] $end
$var reg 1 b clk $end
$var reg 8 c o[7:0] $end
$upscope $end
$scope module reg_3 $end
$var reg 8 d i[7:0] $end
$var reg 1 e clk $end
$var reg 8 f o[7:0] $end
$upscope $end
$scope module reg_4 $end
$var reg 8 g i[7:0] $end
$var reg 1 h clk $end
$var reg 8 i o[7:0] $end
$upscope $end
$upscope $end
$scope module alu1 $end
$var reg 8 j a[7:0] $end
$var reg 8 k b[7:0] $end
$var reg 2 l opfield[1:0] $end
$var reg 8 m o[7:0] $end
$var reg 1 n eq $end
$var reg 2 o temp[1:0] $end
$var reg 8 p sum[7:0] $end
$upscope $end
$upscope $end
$upscope $end
$enddefinitions $end
#0
b01000011 !
0"
b01000011 #
0$
bUUUUUUUU %
bUUUUUUUU &
bUUUUUUUU '
bUUUUUUUU (
0)
bUU *
bUU +
bUU ,
b00000000 -
b00 .
b00 /
b00 0
b00000011 1
12
b00000000 3
b00000000 4
b00000000 5
b00000000 6
b01 7
b00000000 8
bUUUUUUUU 9
0:
0;
b00000011 <
b010 =
0>
0?
0@
0A
0B
0C
0D
0E
0F
0G
0H
b00 I
b00 J
b00 K
0L
b00 M
b00000011 N
1O
b00000000 P
b00000000 Q
b00000011 R
b00000000 S
b00000000 T
b00000000 U
b00000000 V
b00000000 W
b00000000 X
b00000000 Y
b100 Z
0[
0\
0]
b00000011 ^
0_
b00000000 `
b00000000 a
0b
b00000000 c
b00000000 d
0e
b00000000 f
b00000000 g
0h
b00000000 i
b00000000 j
b00000000 k
b01 l
b00000000 m
0n
b10 o
bUUUUUUUU p
#1000000
1"
1$
b00000011 3
b00000011 4
b00000011 5
b00000011 6
b011 =
1>
1?
1@
1A
1B
1C
1D
1E
1F
1L
b00000011 P
b00000011 Q
b00000011 V
1[
1\
1]
1_
b00000011 `
1b
1e
1h
b00000011 j
b00000011 k
#2000000
b00000000 !
0"
b00000000 #
0$
b00000110 1
b00 7
b00000110 8
1;
b00000000 <
b000 =
0>
0?
0@
0A
0B
0C
0D
0E
0F
b10 I
0L
b00000110 N
b00000110 R
0[
0\
0]
b00000110 ^
0_
0b
0e
0h
b00 l
b00000110 m
b00 o
b00000110 p
#3000000
1"
1$
b00001100 1
b00000110 3
b00000110 4
b00000110 5
b00000110 6
b00001100 8
b001 =
1>
1?
1@
1A
1B
1C
1D
1E
1F
1L
b00001100 N
b00000110 P
b00000110 Q
b00001100 R
b00000110 V
1[
1\
1]
b00001100 ^
1_
b00000110 `
1b
1e
1h
b00000110 j
b00000110 k
b00001100 m
b00001100 p
#4000000
b01011010 !
0"
b01011010 #
0$
b01 .
b01 /
b01 0
b11111010 1
b00000000 3
b00000000 4
b00000000 5
b00000000 6
b01 7
0;
b11111010 <
b010 =
0>
0?
0@
0A
0B
0C
0D
0E
0F
b00 I
b01 J
b01 K
0L
b01 M
b11111010 N
b00000000 P
b00000000 Q
b00000110 R
b11111010 S
b00000000 T
b101 Z
0[
0\
0]
b00000110 ^
0_
b11111010 a
0b
b00000000 d
0e
0h
b00000000 j
b00000000 k
b01 l
b10 o
#5000000
1"
1$
b11111010 3
b11111010 4
b11111010 5
b11111010 6
b011 =
1>
1?
1@
1A
1B
1C
1D
1E
1F
1L
b11111010 P
b11111010 Q
b11111010 W
1[
1\
1]
1_
1b
b11111010 c
1e
1h
b11111010 j
b11111010 k
#6000000
b10101011 !
0"
b10101011 #
0$
b10 .
b10 /
b10 0
b00000000 1
02
b00000000 3
b00000000 4
b00000000 5
b00000000 6
b10 7
1:
b11111011 <
b100 =
0>
0?
0@
0A
0B
0C
0D
0E
0F
1G
1H
b01 I
b10 J
b10 K
0L
b10 M
b00000000 N
0O
b00000000 P
b00000000 Q
b010 Z
0[
0\
0]
0_
0b
0e
0h
b00000000 j
b00000000 k
b10 l
1n
b11 o
#7000000
1"
1$
b101 =
1>
1?
1@
1A
1B
1C
1D
1E
1F
1L
1[
1\
1]
1_
1b
1e
1h
#8000000
b00000000 !
0"
b00000000 #
0$
b00 .
b00 /
b00 0
b00001100 1
12
b00000110 3
b00000110 4
b00000110 5
b00000110 6
b00 7
b00001100 8
0:
1;
b00000000 <
b000 =
0>
0?
0@
0A
0B
0C
0D
0E
0F
0G
0H
b10 I
b00 J
b00 K
0L
b00 M
b00001100 N
1O
b00000110 P
b00000110 Q
b00001100 R
b100 Z
0[
0\
0]
b00001100 ^
0_
0b
0e
0h
b00000110 j
b00000110 k
b00 l
b00001100 m
0n
b00 o
b00001100 p
#9000000
1"
1$
b00011000 1
b00001100 3
b00001100 4
b00001100 5
b00001100 6
b00011000 8
b001 =
1>
1?
1@
1A
1B
1C
1D
1E
1F
1L
b00011000 N
b00001100 P
b00001100 Q
b00011000 R
b00001100 V
1[
1\
1]
b00011000 ^
1_
b00001100 `
1b
1e
1h
b00001100 j
b00001100 k
b00011000 m
b00011000 p
#10000000
b01100001 !
0"
b01100001 #
0$
b10 .
b10 /
b10 0
b00000001 1
b00000000 3
b00000000 4
b00000000 5
b00000000 6
b01 7
0;
b00000001 <
b010 =
0>
0?
0@
0A
0B
0C
0D
0E
0F
b00 I
b10 J
b10 K
0L
b10 M
b00000001 N
b00000000 P
b00000000 Q
b00001100 R
b11111010 S
b00000001 T
b110 Z
0[
0\
0]
b00001100 ^
0_
b11111010 a
0b
b00000001 d
0e
0h
b00000000 j
b00000000 k
b01 l
b10 o
#11000000
1"
1$
b00000001 3
b00000001 4
b00000001 5
b00000001 6
b011 =
1>
1?
1@
1A
1B
1C
1D
1E
1F
1L
b00000001 P
b00000001 Q
b00000001 X
1[
1\
1]
1_
1b
1e
b00000001 f
1h
b00000001 j
b00000001 k
#12000000
b00001001 !
0"
b00001001 #
0$
b00 .
b10 /
b01 0
b00001101 1
b00001100 3
b00000001 4
b00001100 5
b00000001 6
b00 7
b00001101 8
1;
b11111001 <
b000 =
0>
0?
0@
0A
0B
0C
0D
0E
0F
b10 I
b00 J
b10 K
0L
b01 M
b00001101 N
b00001100 P
b00000001 Q
b00001100 R
b00001101 S
b101 Z
0[
0\
0]
b00001100 ^
0_
b00001101 a
0b
0e
0h
b00001100 j
b00000001 k
b00 l
b00001101 m
b00 o
b00001101 p
#13000000
1"
1$
b001 =
1>
1?
1@
1A
1B
1C
1D
1E
1F
1L
b00001101 W
1[
1\
1]
1_
1b
b00001101 c
1e
1h
#14000000
b10000011 !
0"
b10000011 #
0$
b00 /
b00 0
b00001100 1
02
b00001100 4
b00001100 6
b10 7
1:
0;
b00000011 <
b100 =
0>
0?
0@
0A
0B
0C
0D
0E
0F
1G
1H
b01 I
b00 K
0L
b00 M
b00001100 N
0O
b00001100 Q
b000 Z
0[
0\
0]
0_
0b
0e
0h
b00001100 k
b10 l
1n
b11 o
#15000000
1"
1$
b101 =
1>
1?
1@
1A
1B
1C
1D
1E
1F
1L
1[
1\
1]
1_
1b
1e
1h
