alu.vhdl
library ieee;
use ieee.std_logic_1164.all;
use IEEE.numeric_std.all;

entity alu is
port(	A:	in std_logic_vector (7 downto 0):= "00000000";
        B:	in std_logic_vector (7 downto 0):= "00000000";
		opField: in std_logic_vector (1 downto 0); --This corresponds to the opfield in the 8-bit ISA instruction
		O:	out std_logic_vector(7 downto 0) := "00000000";
        EQ: out std_logic
);
end alu;

architecture behav of alu is
signal temp: std_logic_vector(1 downto 0);
signal sum: std_logic_vector(7 downto 0);
begin
process(A, B, opField, temp, sum) is
begin
    temp(1) <= opField(1) xor opField(0);
    temp(0) <= (opField(1) and opField(0)) or (opField(1) and not opField(0));

    EQ <= '0';
	if(temp = "00") then
        sum <= std_logic_vector(signed(A) + signed(B));
        O <= sum;
    elsif(temp = "01") then
        sum <= std_logic_vector(signed(A) + signed(not B) + 1); --two's complement subtraction
        O <= sum;
    elsif(temp = "10") then
    else
        if(A = B) then
            EQ <= '1';
        else  
            EQ <= '0';
        end if;
    end if;
end process;
end behav;

register.vhdl
library ieee;
use ieee.std_logic_1164.all;

entity reg is
port(	I:	in std_logic_vector (7 downto 0);
		clk:	in std_logic;
		O:	out std_logic_vector(7 downto 0)
);
end reg;

architecture behav of reg is
begin
process(clk) is
begin
	if(clk='1' and clk'event) then
		O <= I;
	end if;
end process;
end behav;

registerFile.vhdl
library ieee;
use ieee.std_logic_1164.all;

entity registerFile is
port(	rs1:	in std_logic_vector (1 downto 0); -- for loading addresses: 00 = register 1, 01 = register 2, 10 = register 3, 11 = register 4
		rs2: in std_logic_vector (1 downto 0); -- for loading addresses
		clk:    in std_logic;
        ws:        in std_logic_vector(1 downto 0); -- write selects address: 00 = register 1, 01 = register 2, 10 = register 3, 11 = register 4
		wd:		in std_logic_vector(7 downto 0); -- write data
        we:		in std_logic; -- positive level triggering in problem 3
		rd1:		out std_logic_vector (7 downto 0); -- 0: don't do anything; 1: shift_reg is enabled
        rd2:		out std_logic_vector (7 downto 0) -- 0: don't do anything; 1: shift_reg is enabled
);
end registerFile;


architecture behav of registerFile is

component reg
port (	I:	in std_logic_vector (7 downto 0);
        clk:    in std_logic; 
        O:	out std_logic_vector(7 downto 0)
);
end component;

signal i1: std_logic_vector(7 downto 0) := "00000000";
signal i2: std_logic_vector(7 downto 0) := "00000000";
signal i3: std_logic_vector(7 downto 0) := "00000000";
signal i4: std_logic_vector(7 downto 0) := "00000000";
signal o1: std_logic_vector(7 downto 0);
signal o2: std_logic_vector(7 downto 0);
signal o3: std_logic_vector(7 downto 0);
signal o4: std_logic_vector(7 downto 0);
signal clockSig: std_logic;
begin

--  Component instantiation.
reg_1: reg port map ( I => i1, clk => clockSig, O => o1); --left 4 bits
reg_2: reg port map ( I => i2, clk => clockSig, O => o2); --right 4 bits
reg_3: reg port map ( I => i3, clk => clockSig, O => o3); --right 4 bits
reg_4: reg port map ( I => i4, clk => clockSig, O => o4); --right 4 bits

process(clk) is
begin
    if(clk='1' and clk'event) then
        if(rs1="00") then --rd1 should output register 1
        rd1 <= o1;

        elsif(rs1="01") then --rd1 should output register 2
        rd1 <= o2;
        
        elsif(rs1="10") then --rd1 should output register 3
        rd1 <= o3;
        
        else --rd1 should output register 1
        rd1 <= o4;
        
        end if;
        if(rs2="00") then --rd2 should output register 1
        rd2 <= o1;

        elsif(rs2="01") then --rd2 should output register 2
        rd2 <= o2;
        
        elsif(rs2="10") then --rd2 should output register 3
        rd2 <= o3;
        
        else --rd2 should output register 1
        rd2 <= o4;

        end if;
        if(we='1') then
            if(ws="00") then --set i2 to wd
                i1 <= wd;
                
            elsif(ws="01") then --set i2 to wd
               i2 <= wd;
                
            elsif(ws="10") then --set i3 to wd
                i3 <= wd;
                
            else --set i4 to wd
                i4 <= wd;

            end if;
        end if;
        clockSig <= clk;
    end if;
end process;

end behav;

calculator.vhdl
library ieee;
use ieee.std_logic_1164.all;
use IEEE.numeric_std.all;

entity calculator is 
    port( --opcode key: ADD = 00, SUB = 11, LOAD = 01, CMP/PRINT = 10
        I: in std_logic_vector(7 downto 0) := "00000000"; --format is: opcode (7 downto 6), rs (5 downto 4), rt (3 downto 2), rd (1 downto 0) for rType, 
        clk: in std_logic                                 --opcode(7 downto 6), rd(5 downto 4), im (3 downto 0) for I-type
    );
end entity calculator;

architecture behavioral of calculator is
component alu is  --this is the alu need to add 1 because vhdl name
    port(	A:	in std_logic_vector (7 downto 0);
        B:	in std_logic_vector (7 downto 0);
		opField: in std_logic_vector (1 downto 0); --This corresponds to the opfield in the 8-bit ISA instruction
		O:	out std_logic_vector(7 downto 0);
        EQ: out std_logic
);
end component alu;

component registerFile is
    port(	rs1:	in std_logic_vector (1 downto 0); -- for loading addresses: 00 = register 1, 01 = register 2, 10 = register 3, 11 = register 4
		rs2: in std_logic_vector (1 downto 0); -- for loading addresses
		clk:    in std_logic;
        ws:        in std_logic_vector(1 downto 0); -- write selects address: 00 = register 1, 01 = register 2, 10 = register 3, 11 = register 4
		wd:		in std_logic_vector(7 downto 0); -- write data
        we:		in std_logic; -- positive level triggering in problem 3
		rd1:		out std_logic_vector (7 downto 0); -- 0: don't do anything; 1: shift_reg is enabled
        rd2:		out std_logic_vector (7 downto 0) -- 0: don't do anything; 1: shift_reg is enabled
);
end component registerFile;

signal regOut1, regOut2, regOut3, regOut4: std_logic_vector(7 downto 0);
signal we_signal : std_logic :='0'; --write enable = 1 for all except branch/compare
signal regIn1, regIn2, ws_signal :std_logic_vector(1 downto 0);


signal immediateOutput : std_logic_vector(7 downto 0) := "00000000";


signal regFileInputA, regFileInputB, regDest: std_logic_vector(1 downto 0);
signal regWrite : std_logic_vector(7 downto 0);
signal writeEnable : std_logic;
signal regFileOutputA, regFileOutputB: std_logic_vector(7 downto 0);
signal aluInputA, aluInputB: std_logic_vector(7 downto 0);
signal aluOpField: std_logic_vector(1 downto 0);
signal aluOutput, aluOutputBuffer : std_logic_vector(7 downto 0);
signal aluBranch: std_logic;
signal rType : std_logic; --signifies whether it is add/subtract (1) or load (0)
signal immExtend : std_logic_vector(7 downto 0); --immedate 0 or 1 padded
signal clk_signal, clk_signal2, clk_signal3, clk_signal4, clk_signal5, clk_signal6, clk_signal7, clk_signal8, clk_signal9 : std_logic;
signal opCodeAndClk: std_logic_vector(2 downto 0);

--signal ws_signal : std_logic_vector (1 downto 0) := "00";
begin  
    regFile : registerFile port map(rs1 => regFileInputA, rs2 => regFileInputB, clk => clk_signal9, ws => regDest, wd=>regWrite, we => writeEnable,rd1 =>regFileOutputA, rd2 =>regFileOutputB  );
    alu1: alu port map(A => aluInputA, B => aluInputB, opField => aluOpField, O => aluOutput, EQ => aluBranch);

    with I(7 downto 6) select 
        rType <= '0' when "01", --load is i type
                 '0' when "10", --print i guess
                 '1' when others;
    
    with rType select
        regDest <= I(1 downto 0) when '1', --add/sub has regDest at last 2 bits
                   I(5 downto 4) when others; --load is at 2 bits 2 to the left 
    
    regFileInputA <= I(5 downto 4);



    with rType select
        regFileInputB <= I(3 downto 2) when '1', --add/sub format
                         I(5 downto 4) when others; --just to have an expected return value, the registerFile will select rd as its A and B input on load

--right now the aluoutput defaults to "0000000" because that's how it should be, we need a way to change regWrite to wait for aluOutput to stabilize before sending it in
    with rType select
        regWrite <= aluOutput when '1', --add/sub gets regWrite from alu
                    immExtend when others;
    
    with I(3) select
        immExtend <= "0000" & I(3 downto 0) when '0',
                     "1111" & I(3 downto 0) when others;

    aluOpField <= I(7 downto 6);

    aluInputA <= regFileOutputA;
    aluInputB <= regFileOutputB;

    with opCodeAndClk select --right now ignores clock
        writeEnable <= '1' when "001",
                       '1' when "111",
                       '1' when "011",
                       '0' when others;
    
    opCodeAndClk <= I(7 downto 6) & clk;
    





    process(clk)
    begin
        clk_signal <= clk;

    end process;

    process(clk_signal)
    begin

        clk_signal2 <= clk_signal;
    end process;

    process(clk_signal2)
    begin
        clk_signal3 <= clk_signal2;
    end process;

    process(clk_signal3)
    begin
        
        clk_signal4 <= clk_signal3;
    end process;

    process(clk_signal4)
    begin

        clk_signal5 <= clk_signal4;
    end process;

    process(clk_signal5)
    begin
        clk_signal6 <= clk_signal5;
    end process;

    process(clk_signal6)
    begin
        
        clk_signal7 <= clk_signal6;
    end process;

    process(clk_signal7)
    begin

        clk_signal8 <= clk_signal7;

    end process;

    process(clk_signal8)
    begin
        
        clk_signal9 <= clk_signal8;
        report "regWrite: " & integer'image(to_integer(signed(RegWrite))); 

    end process;

end architecture behavioral;

calculator_tb.vhdl
library ieee;
use ieee.std_logic_1164.all;

--  A testbench has no ports.
entity calculator_tb is
end calculator_tb;

architecture behav of calculator_tb is
--  Declaration of the component that will be instantiated.
component calculator
port(	I: in std_logic_vector(7 downto 0);
        clk: in std_logic
);
end component;
--  Specifies which entity is bound with the component.
signal i: std_logic_vector(7 downto 0);
signal clock: std_logic;
begin
--  Component instantiation.
calculator1 : calculator port map(I => I, clk => clock);

--  This process does the real job.
process
type pattern_type is record
--  The inputs of the shift_reg.
i: std_logic_vector(7 downto 0);
clock: std_logic;
end record;
--  The patterns to apply.
type pattern_array is array (natural range <>) of pattern_type;
constant patterns : pattern_array := -- Order goes: Input address rs1,rs2,ws ; input data rd1,rd2,wd ; we clk
(("00000000", '1'), --add r1 and r1 to r1 (0000 + 0000 = 0000)
("00000000", '0'),
("01000010", '1'), --set r1 to 0010
("01000111", '0'),
("00000000", '1'), --add r1 and r1 to r1 (0010 + 0010 = 0100)
("00000000", '0'),
("01011010", '1'), --set r2 to 1010
("01001000", '0'),
("01100001", '1'), --set r3 to 0001
("01000011", '0'),
("00001001", '1'), --add r1 and r3 and put it in r2 (0100 + 0001 = 0101)
("01000011", '0'),
("01110101", '1'), --set r4 to 0101
("01101011", '0')); --clock enable = 0, won't write to register
begin
--  Check each pattern.
for n in patterns'range loop
--  Set the inputs.
i <= patterns(n).i;
clock <= patterns(n).clock;

--  Wait for the results.
wait for 1 ns;
--  Check the outputs.
end loop;
assert false report "end of test" severity note;
--  Wait forever; this will finish the simulation.
wait;
end process;
end behav;

calculator.vcd
$date
  Fri May 21 14:28:49 2021
$end
$version
  GHDL v0
$end
$timescale
  1 fs
$end
$scope module standard $end
$upscope $end
$scope module std_logic_1164 $end
$upscope $end
$scope module numeric_std $end
$upscope $end
$scope module calculator_tb $end
$var reg 8 ! i[7:0] $end
$var reg 1 " clock $end
$scope module calculator1 $end
$var reg 8 # i[7:0] $end
$var reg 1 $ clk $end
$var reg 8 % regout1[7:0] $end
$var reg 8 & regout2[7:0] $end
$var reg 8 ' regout3[7:0] $end
$var reg 8 ( regout4[7:0] $end
$var reg 1 ) we_signal $end
$var reg 2 * regin1[1:0] $end
$var reg 2 + regin2[1:0] $end
$var reg 2 , ws_signal[1:0] $end
$var reg 8 - immediateoutput[7:0] $end
$var reg 2 . regfileinputa[1:0] $end
$var reg 2 / regfileinputb[1:0] $end
$var reg 2 0 regdest[1:0] $end
$var reg 8 1 regwrite[7:0] $end
$var reg 1 2 writeenable $end
$var reg 8 3 regfileoutputa[7:0] $end
$var reg 8 4 regfileoutputb[7:0] $end
$var reg 8 5 aluinputa[7:0] $end
$var reg 8 6 aluinputb[7:0] $end
$var reg 2 7 aluopfield[1:0] $end
$var reg 8 8 aluoutput[7:0] $end
$var reg 8 9 aluoutputbuffer[7:0] $end
$var reg 1 : alubranch $end
$var reg 1 ; rtype $end
$var reg 8 < immextend[7:0] $end
$var reg 1 = clk_signal $end
$var reg 1 > clk_signal2 $end
$var reg 1 ? clk_signal3 $end
$var reg 1 @ clk_signal4 $end
$var reg 1 A clk_signal5 $end
$var reg 1 B clk_signal6 $end
$var reg 1 C clk_signal7 $end
$var reg 1 D clk_signal8 $end
$var reg 1 E clk_signal9 $end
$var reg 3 F opcodeandclk[2:0] $end
$scope module regfile $end
$var reg 2 G rs1[1:0] $end
$var reg 2 H rs2[1:0] $end
$var reg 1 I clk $end
$var reg 2 J ws[1:0] $end
$var reg 8 K wd[7:0] $end
$var reg 1 L we $end
$var reg 8 M rd1[7:0] $end
$var reg 8 N rd2[7:0] $end
$var reg 8 O i1[7:0] $end
$var reg 8 P i2[7:0] $end
$var reg 8 Q i3[7:0] $end
$var reg 8 R i4[7:0] $end
$var reg 8 S o1[7:0] $end
$var reg 8 T o2[7:0] $end
$var reg 8 U o3[7:0] $end
$var reg 8 V o4[7:0] $end
$var reg 1 W clocksig $end
$scope module reg_1 $end
$var reg 8 X i[7:0] $end
$var reg 1 Y clk $end
$var reg 8 Z o[7:0] $end
$upscope $end
$scope module reg_2 $end
$var reg 8 [ i[7:0] $end
$var reg 1 \ clk $end
$var reg 8 ] o[7:0] $end
$upscope $end
$scope module reg_3 $end
$var reg 8 ^ i[7:0] $end
$var reg 1 _ clk $end
$var reg 8 ` o[7:0] $end
$upscope $end
$scope module reg_4 $end
$var reg 8 a i[7:0] $end
$var reg 1 b clk $end
$var reg 8 c o[7:0] $end
$upscope $end
$upscope $end
$scope module alu1 $end
$var reg 8 d a[7:0] $end
$var reg 8 e b[7:0] $end
$var reg 2 f opfield[1:0] $end
$var reg 8 g o[7:0] $end
$var reg 1 h eq $end
$var reg 2 i temp[1:0] $end
$var reg 8 j sum[7:0] $end
$upscope $end
$upscope $end
$upscope $end
$enddefinitions $end
#0
b00000000 !
1"
b00000000 #
1$
bUUUUUUUU %
bUUUUUUUU &
bUUUUUUUU '
bUUUUUUUU (
0)
bUU *
bUU +
bUU ,
b00000000 -
b00 .
b00 /
b00 0
b00000000 1
12
b00000000 3
b00000000 4
b00000000 5
b00000000 6
b00 7
b00000000 8
bUUUUUUUU 9
0:
1;
b00000000 <
1=
1>
1?
1@
1A
1B
1C
1D
1E
b001 F
b00 G
b00 H
1I
b00 J
b00000000 K
1L
b00000000 M
b00000000 N
b00000000 O
b00000000 P
b00000000 Q
b00000000 R
b00000000 S
b00000000 T
b00000000 U
b00000000 V
1W
b00000000 X
1Y
b00000000 Z
b00000000 [
1\
b00000000 ]
b00000000 ^
1_
b00000000 `
b00000000 a
1b
b00000000 c
b00000000 d
b00000000 e
b00 f
b00000000 g
0h
b00 i
b00000000 j
#1000000
0"
0$
02
0=
0>
0?
0@
0A
0B
0C
0D
0E
b000 F
0I
0L
0W
0Y
0\
0_
0b
#2000000
b01000010 !
1"
b01000010 #
1$
b00 0
b00000010 1
12
b00000010 3
b00000010 4
b00000010 5
b00000010 6
b01 7
0;
b00000010 <
1=
1>
1?
1@
1A
1B
1C
1D
1E
b011 F
1I
b00 J
b00000010 K
1L
b00000010 M
b00000010 N
b00000010 O
b00000010 S
1W
b00000010 X
1Y
b00000010 Z
1\
1_
1b
b00000010 d
b00000010 e
b01 f
b10 i
#3000000
b01000111 !
0"
b01000111 #
0$
b00000111 1
02
b00000111 <
0=
0>
0?
0@
0A
0B
0C
0D
0E
b010 F
0I
b00000111 K
0L
0W
0Y
0\
0_
0b
#4000000
b00000000 !
1"
b00000000 #
1$
b00001000 1
12
b00000100 3
b00000100 4
b00000100 5
b00000100 6
b00 7
b00001000 8
1;
b00000000 <
1=
1>
1?
1@
1A
1B
1C
1D
1E
b001 F
1I
b00001000 K
1L
b00000100 M
b00000100 N
b00000100 O
b00000100 S
1W
b00000100 X
1Y
b00000100 Z
1\
1_
1b
b00000100 d
b00000100 e
b00 f
b00001000 g
b00 i
b00001000 j
#5000000
0"
0$
02
0=
0>
0?
0@
0A
0B
0C
0D
0E
b000 F
0I
0L
0W
0Y
0\
0_
0b
#6000000
b01011010 !
1"
b01011010 #
1$
b01 .
b01 /
b01 0
b11111010 1
12
b11111010 3
b11111010 4
b11111010 5
b11111010 6
b01 7
0;
b11111010 <
1=
1>
1?
1@
1A
1B
1C
1D
1E
b011 F
b01 G
b01 H
1I
b01 J
b11111010 K
1L
b11111010 M
b11111010 N
b11111010 P
b11111010 T
1W
1Y
b11111010 [
1\
b11111010 ]
1_
1b
b11111010 d
b11111010 e
b01 f
b10 i
#7000000
b01001000 !
0"
b01001000 #
0$
b00 .
b00 /
b00 0
b11111000 1
02
b00000100 3
b00000100 4
b00000100 5
b00000100 6
b11111000 <
0=
0>
0?
0@
0A
0B
0C
0D
0E
b010 F
b00 G
b00 H
0I
b00 J
b11111000 K
0L
b00000100 M
b00000100 N
0W
0Y
0\
0_
0b
b00000100 d
b00000100 e
#8000000
b01100001 !
1"
b01100001 #
1$
b10 .
b10 /
b10 0
b00000001 1
12
b00000001 3
b00000001 4
b00000001 5
b00000001 6
b00000001 <
1=
1>
1?
1@
1A
1B
1C
1D
1E
b011 F
b10 G
b10 H
1I
b10 J
b00000001 K
1L
b00000001 M
b00000001 N
b00000001 Q
b00000001 U
1W
1Y
1\
b00000001 ^
1_
b00000001 `
1b
b00000001 d
b00000001 e
#9000000
b01000011 !
0"
b01000011 #
0$
b00 .
b00 /
b00 0
b00000011 1
02
b00000100 3
b00000100 4
b00000100 5
b00000100 6
b00000011 <
0=
0>
0?
0@
0A
0B
0C
0D
0E
b010 F
b00 G
b00 H
0I
b00 J
b00000011 K
0L
b00000100 M
b00000100 N
0W
0Y
0\
0_
0b
b00000100 d
b00000100 e
#10000000
b00001001 !
1"
b00001001 #
1$
b10 /
b01 0
b00000101 1
12
b00000001 4
b00000001 6
b00 7
b00000101 8
1;
b11111001 <
1=
1>
1?
1@
1A
1B
1C
1D
1E
b001 F
b10 H
1I
b01 J
b00000101 K
1L
b00000001 N
b00000101 P
b00000101 T
1W
1Y
b00000101 [
1\
b00000101 ]
1_
1b
b00000001 e
b00 f
b00000101 g
b00 i
b00000101 j
#11000000
b01000011 !
0"
b01000011 #
0$
b00 /
b00 0
b00000011 1
02
b00000100 4
b00000100 6
b01 7
0;
b00000011 <
0=
0>
0?
0@
0A
0B
0C
0D
0E
b010 F
b00 H
0I
b00 J
b00000011 K
0L
b00000100 N
0W
0Y
0\
0_
0b
b00000100 e
b01 f
b10 i
#12000000
b01110101 !
1"
b01110101 #
1$
b11 .
b11 /
b11 0
b00000101 1
12
b00000101 3
b00000101 4
b00000101 5
b00000101 6
b00000101 <
1=
1>
1?
1@
1A
1B
1C
1D
1E
b011 F
b11 G
b11 H
1I
b11 J
b00000101 K
1L
b00000101 M
b00000101 N
b00000101 R
b00000101 V
1W
1Y
1\
1_
b00000101 a
1b
b00000101 c
b00000101 d
b00000101 e
#13000000
b01101011 !
0"
b01101011 #
0$
b10 .
b10 /
b10 0
b11111011 1
02
b00000001 3
b00000001 4
b00000001 5
b00000001 6
b11111011 <
0=
0>
0?
0@
0A
0B
0C
0D
0E
b010 F
b10 G
b10 H
0I
b10 J
b11111011 K
0L
b00000001 M
b00000001 N
0W
0Y
0\
0_
0b
b00000001 d
b00000001 e
