alu.vhdl
library ieee;
use ieee.std_logic_1164.all;
use IEEE.numeric_std.all;

entity alu is
port(	A:	in std_logic_vector (7 downto 0):= "00000000";
        B:	in std_logic_vector (7 downto 0):= "00000000";
		opField: in std_logic_vector (1 downto 0); --This corresponds to the opfield in the 8-bit ISA instruction
		O:	out std_logic_vector(7 downto 0) := "00000000";
        EQ: out std_logic
);
end alu;

architecture behav of alu is
signal temp: std_logic_vector(1 downto 0);
signal sum: std_logic_vector(7 downto 0);
begin
process(A, B, opField, temp, sum) is
begin
    temp(1) <= opField(1) xor opField(0);
    temp(0) <= (opField(1) and opField(0)) or (opField(1) and not opField(0));

    EQ <= '0';
	if(temp = "00") then
        sum <= std_logic_vector(signed(A) + signed(B));
        O <= sum;
    elsif(temp = "01") then
        sum <= std_logic_vector(signed(A) + signed(not B) + 1); --two's complement subtraction
        O <= sum;
    elsif(temp = "10") then
    else
        if(A = B) then
            EQ <= '1';
        else  
            EQ <= '0';
        end if;
    end if;
end process;
end behav;

register.vhdl
library ieee;
use ieee.std_logic_1164.all;

entity reg is
port(	I:	in std_logic_vector (7 downto 0);
		clk:	in std_logic;
		O:	out std_logic_vector(7 downto 0)
);
end reg;

architecture behav of reg is
begin
process(clk) is
begin
	if(clk='1' and clk'event) then
		O <= I;
	end if;
end process;
end behav;

registerFile.vhdl
library ieee;
use ieee.std_logic_1164.all;

entity registerFile is
port(	rs1:	in std_logic_vector (1 downto 0); -- for loading addresses: 00 = register 1, 01 = register 2, 10 = register 3, 11 = register 4
		rs2: in std_logic_vector (1 downto 0); -- for loading addresses
		clk:    in std_logic;
        ws:        in std_logic_vector(1 downto 0); -- write selects address: 00 = register 1, 01 = register 2, 10 = register 3, 11 = register 4
		wd:		in std_logic_vector(7 downto 0); -- write data
        we:		in std_logic; -- positive level triggering in problem 3
		rd1:		out std_logic_vector (7 downto 0); -- 0: don't do anything; 1: shift_reg is enabled
        rd2:		out std_logic_vector (7 downto 0) -- 0: don't do anything; 1: shift_reg is enabled
);
end registerFile;


architecture behav of registerFile is

component reg
port (	I:	in std_logic_vector (7 downto 0);
        clk:    in std_logic; 
        O:	out std_logic_vector(7 downto 0)
);
end component;

signal i1: std_logic_vector(7 downto 0) := "00000000";
signal i2: std_logic_vector(7 downto 0) := "00000000";
signal i3: std_logic_vector(7 downto 0) := "00000000";
signal i4: std_logic_vector(7 downto 0) := "00000000";
signal o1: std_logic_vector(7 downto 0);
signal o2: std_logic_vector(7 downto 0);
signal o3: std_logic_vector(7 downto 0);
signal o4: std_logic_vector(7 downto 0);
signal clockSig: std_logic;
begin

--  Component instantiation.
reg_1: reg port map ( I => i1, clk => clockSig, O => o1); --left 4 bits
reg_2: reg port map ( I => i2, clk => clockSig, O => o2); --right 4 bits
reg_3: reg port map ( I => i3, clk => clockSig, O => o3); --right 4 bits
reg_4: reg port map ( I => i4, clk => clockSig, O => o4); --right 4 bits

process(clk) is
begin
    if(clk='1' and clk'event) then
        if(rs1="00") then --rd1 should output register 1
        rd1 <= o1;

        elsif(rs1="01") then --rd1 should output register 2
        rd1 <= o2;
        
        elsif(rs1="10") then --rd1 should output register 3
        rd1 <= o3;
        
        else --rd1 should output register 1
        rd1 <= o4;
        
        end if;
        if(rs2="00") then --rd2 should output register 1
        rd2 <= o1;

        elsif(rs2="01") then --rd2 should output register 2
        rd2 <= o2;
        
        elsif(rs2="10") then --rd2 should output register 3
        rd2 <= o3;
        
        else --rd2 should output register 1
        rd2 <= o4;

        end if;
        if(we='1') then
            if(ws="00") then --set i2 to wd
                i1 <= wd;
                
            elsif(ws="01") then --set i2 to wd
               i2 <= wd;
                
            elsif(ws="10") then --set i3 to wd
                i3 <= wd;
                
            else --set i4 to wd
                i4 <= wd;

            end if;
        end if;
        clockSig <= clk;
    end if;
end process;

end behav;

calculator.vhdl
library ieee;
use ieee.std_logic_1164.all;
use IEEE.numeric_std.all;

entity calculator is 
    port( --opcode key: ADD = 00, SUB = 11, LOAD = 01, CMP/PRINT = 10
        I: in std_logic_vector(7 downto 0) := "00000000"; --format is: opcode (7 downto 6), rd (5 downto 4), rs (3 downto 2), rt (1 downto 0)
        clk: in std_logic
    );
end entity calculator;

architecture behavioral of calculator is
component alu is  --this is the alu need to add 1 because vhdl name
    port(	A:	in std_logic_vector (7 downto 0);
        B:	in std_logic_vector (7 downto 0);
		opField: in std_logic_vector (1 downto 0); --This corresponds to the opfield in the 8-bit ISA instruction
		O:	out std_logic_vector(7 downto 0);
        EQ: out std_logic
);
end component alu;

component registerFile is
    port(	rs1:	in std_logic_vector (1 downto 0); -- for loading addresses: 00 = register 1, 01 = register 2, 10 = register 3, 11 = register 4
		rs2: in std_logic_vector (1 downto 0); -- for loading addresses
		clk:    in std_logic;
        ws:        in std_logic_vector(1 downto 0); -- write selects address: 00 = register 1, 01 = register 2, 10 = register 3, 11 = register 4
		wd:		in std_logic_vector(7 downto 0); -- write data
        we:		in std_logic; -- positive level triggering in problem 3
		rd1:		out std_logic_vector (7 downto 0); -- 0: don't do anything; 1: shift_reg is enabled
        rd2:		out std_logic_vector (7 downto 0) -- 0: don't do anything; 1: shift_reg is enabled
);
end component registerFile;

signal regOut1, regOut2, RegWrite : std_logic_vector(7 downto 0) := "00000000";
signal branch, we_signal : std_logic :='0'; --write enable = 1 for all except branch/compare
signal regIn1, regIn2, ws_signal :std_logic_vector(1 downto 0);
signal aluOutput : std_logic_vector(7 downto 0) := "00000000";
signal rType : std_logic := '0'; --signifies whether it is add/subtract (1) or load (0)
signal immediateOutput : std_logic_vector(7 downto 0) := "00000000";
signal clk_signal : std_logic;
--signal ws_signal : std_logic_vector (1 downto 0) := "00";
begin  
    regFile : registerFile port map(rs1 => I(5 downto 4), rs2 => I(3 downto 2), clk => clk_signal, ws => ws_signal, wd=>regWrite, we => we_signal,rd1 =>regOut1, rd2 =>regOut2  );
    alu1: alu port map(A => regOut1, B => regOut2, opField => I(7 downto 6), O => aluOutput, EQ => branch);
    we_signal <= (I(7) and I(6)) or (not I(7) and not I(6)) or (not I(7) and I(6)); --write enable for when add, sub, or load is called
    rType <= (I(7) and I(6)) or (not I(7) and not I(6)); --add or subtract makes it 1
    --immediateOutput(3 downto 0) <= I(3 downto 0);
    with I(3) select immediateOutput(7 downto 0) <=
        "0000" & I(3 downto 0) when '0',
        "1111" & I(3 downto 0) when others;

        --PUT LOAD IN A PROCESS STATEMENT
    
    process(clk)
    begin
        if(rType = '1') then
            regWrite <= aluOutput;
        else
            regWrite <= immediateOutput;
        end if;
        if(clk = '1') then
            if(rType = '0') then --load
                ws_signal <= I(5 downto 4);
                report "calling load selecting register with address: " & integer'image(to_integer(1 + unsigned("0" & I(5 downto 4))));
                report "RegWrite value: " & integer'image(to_integer(signed(RegWrite)));
            else --add/sub
                ws_signal <= I(1 downto 0);
                report "calling add or subtract selecting register with address: " & integer'image(to_integer(1 + unsigned("0" & I(1 downto 0))));
                report "RegWrite value: " & integer'image(to_integer(signed(RegWrite)));
            end if;
        end if;
        
        --report "regOut1 value: " & integer'image(to_integer(signed(regOut1)));
        --report "regOut2 value: " & integer'image(to_integer(signed(regOut2)));
        --report "Reg Output Value of we_signal " & std_logic'image(we_signal);
        clk_signal <= clk;
    end process;


end architecture behavioral;

calculator_tb.vhdl
library ieee;
use ieee.std_logic_1164.all;

--  A testbench has no ports.
entity calculator_tb is
end calculator_tb;

architecture behav of calculator_tb is
--  Declaration of the component that will be instantiated.
component calculator
port(	I: in std_logic_vector(7 downto 0);
        clk: in std_logic
);
end component;
--  Specifies which entity is bound with the component.
signal i: std_logic_vector(7 downto 0);
signal clock: std_logic;
begin
--  Component instantiation.
calculator1 : calculator port map(I => I, clk => clock);

--  This process does the real job.
process
type pattern_type is record
--  The inputs of the shift_reg.
i: std_logic_vector(7 downto 0);
clock: std_logic;
end record;
--  The patterns to apply.
type pattern_array is array (natural range <>) of pattern_type;
constant patterns : pattern_array := -- Order goes: Input address rs1,rs2,ws ; input data rd1,rd2,wd ; we clk
(("00000000", '0'),
("01000111", '1'), --set r1 to 0111
("01010001", '0'),
("01011010", '1'), --set r2 to 1010
("01001000", '0'),
("01100001", '1'), --set r3 to 0001
("01000011", '0'),
("01110101", '1'), --set r4 to 0101
("01101011", '0')); --clock enable = 0, won't write to register
begin
--  Check each pattern.
for n in patterns'range loop
--  Set the inputs.
i <= patterns(n).i;
clock <= patterns(n).clock;

--  Wait for the results.
wait for 1 ns;
--  Check the outputs.
end loop;
assert false report "end of test" severity note;
--  Wait forever; this will finish the simulation.
wait;
end process;
end behav;

calculator2.vcd
$date
  Thu May 20 21:59:17 2021
$end
$version
  GHDL v0
$end
$timescale
  1 fs
$end
$scope module standard $end
$upscope $end
$scope module std_logic_1164 $end
$upscope $end
$scope module numeric_std $end
$upscope $end
$scope module calculator_tb $end
$var reg 8 ! i[7:0] $end
$var reg 1 " clock $end
$scope module calculator1 $end
$var reg 8 # i[7:0] $end
$var reg 1 $ clk $end
$var reg 8 % regout1[7:0] $end
$var reg 8 & regout2[7:0] $end
$var reg 8 ' regwrite[7:0] $end
$var reg 1 ( branch $end
$var reg 1 ) we_signal $end
$var reg 2 * regin1[1:0] $end
$var reg 2 + regin2[1:0] $end
$var reg 2 , ws_signal[1:0] $end
$var reg 8 - aluoutput[7:0] $end
$var reg 1 . rtype $end
$var reg 8 / immediateoutput[7:0] $end
$var reg 1 0 clk_signal $end
$scope module regfile $end
$var reg 2 1 rs1[1:0] $end
$var reg 2 2 rs2[1:0] $end
$var reg 1 3 clk $end
$var reg 2 4 ws[1:0] $end
$var reg 8 5 wd[7:0] $end
$var reg 1 6 we $end
$var reg 8 7 rd1[7:0] $end
$var reg 8 8 rd2[7:0] $end
$var reg 8 9 i1[7:0] $end
$var reg 8 : i2[7:0] $end
$var reg 8 ; i3[7:0] $end
$var reg 8 < i4[7:0] $end
$var reg 8 = o1[7:0] $end
$var reg 8 > o2[7:0] $end
$var reg 8 ? o3[7:0] $end
$var reg 8 @ o4[7:0] $end
$var reg 1 A clocksig $end
$scope module reg_1 $end
$var reg 8 B i[7:0] $end
$var reg 1 C clk $end
$var reg 8 D o[7:0] $end
$upscope $end
$scope module reg_2 $end
$var reg 8 E i[7:0] $end
$var reg 1 F clk $end
$var reg 8 G o[7:0] $end
$upscope $end
$scope module reg_3 $end
$var reg 8 H i[7:0] $end
$var reg 1 I clk $end
$var reg 8 J o[7:0] $end
$upscope $end
$scope module reg_4 $end
$var reg 8 K i[7:0] $end
$var reg 1 L clk $end
$var reg 8 M o[7:0] $end
$upscope $end
$upscope $end
$scope module alu1 $end
$var reg 8 N a[7:0] $end
$var reg 8 O b[7:0] $end
$var reg 2 P opfield[1:0] $end
$var reg 8 Q o[7:0] $end
$var reg 1 R eq $end
$var reg 2 S temp[1:0] $end
$var reg 8 T sum[7:0] $end
$upscope $end
$upscope $end
$upscope $end
$enddefinitions $end
#0
b00000000 !
0"
b00000000 #
0$
b00000000 %
b00000000 &
b1111UUUU '
0(
1)
bUU *
bUU +
bUU ,
b00000000 -
1.
b00000000 /
00
b00 1
b00 2
03
bUU 4
b1111UUUU 5
16
b00000000 7
b00000000 8
b00000000 9
b00000000 :
b00000000 ;
b00000000 <
b00000000 =
b00000000 >
b00000000 ?
b00000000 @
0A
b00000000 B
0C
b00000000 D
b00000000 E
0F
b00000000 G
b00000000 H
0I
b00000000 J
b00000000 K
0L
b00000000 M
b00000000 N
b00000000 O
b00 P
b00000000 Q
0R
b00 S
b00000000 T
#1000000
b01000111 !
1"
b01000111 #
1$
b00000000 '
b11 ,
0.
b00000111 /
10
b01 2
13
b11 4
b00000000 5
1A
1C
1F
1I
1L
b01 P
b10 S
#2000000
b01010001 !
0"
b01010001 #
0$
b00000111 '
b00000001 /
00
b01 1
b00 2
03
b00000111 5
0A
0C
0F
0I
0L
#3000000
b01011010 !
1"
b01011010 #
1$
b00000001 %
b00000001 '
b01 ,
b11111010 /
10
b10 2
13
b01 4
b00000001 5
b00000001 7
b00000001 :
b00000001 >
1A
1C
b00000001 E
1F
b00000001 G
1I
1L
b00000001 N
#4000000
b01001000 !
0"
b01001000 #
0$
b00000000 %
b11111010 '
b11111000 /
00
b00 1
03
b11111010 5
b00000000 7
0A
0C
0F
0I
0L
b00000000 N
#5000000
b01100001 !
1"
b01100001 #
1$
b11111000 %
b11111000 '
b10 ,
b00000001 /
10
b10 1
b00 2
13
b10 4
b11111000 5
b11111000 7
b11111000 ;
b11111000 ?
1A
1C
1F
b11111000 H
1I
b11111000 J
1L
b11111000 N
#6000000
b01000011 !
0"
b01000011 #
0$
b00000000 %
b00000001 '
b00000011 /
00
b00 1
03
b00000001 5
b00000000 7
0A
0C
0F
0I
0L
b00000000 N
#7000000
b01110101 !
1"
b01110101 #
1$
b00000011 %
b00000001 &
b00000011 '
b11 ,
b00000101 /
10
b11 1
b01 2
13
b11 4
b00000011 5
b00000011 7
b00000001 8
b00000011 <
b00000011 @
1A
1C
1F
1I
b00000011 K
1L
b00000011 M
b00000011 N
b00000001 O
#8000000
b01101011 !
0"
b01101011 #
0$
b11111000 %
b11111000 &
b00000101 '
b11111011 /
00
b10 1
b10 2
03
b00000101 5
b11111000 7
b11111000 8
0A
0C
0F
0I
0L
b11111000 N
b11111000 O
