alu.vhdl
library ieee;
use ieee.std_logic_1164.all;
use IEEE.numeric_std.all;

entity alu is
port(	A:	in std_logic_vector (7 downto 0):= "00000000";
        B:	in std_logic_vector (7 downto 0):= "00000000";
		opField: in std_logic_vector (1 downto 0); --This corresponds to the opfield in the 8-bit ISA instruction
		O:	out std_logic_vector(7 downto 0) := "00000000";
        EQ: out std_logic
);
end alu;

architecture behav of alu is
signal temp: std_logic_vector(1 downto 0);
signal sum: std_logic_vector(7 downto 0);
begin
process(A, B, opField, temp, sum) is
begin
    temp(1) <= opField(1) xor opField(0);
    temp(0) <= (opField(1) and opField(0)) or (opField(1) and not opField(0));

    EQ <= '0';
	if(temp = "00") then
        sum <= std_logic_vector(signed(A) + signed(B));
        O <= sum;
    elsif(temp = "01") then
        sum <= std_logic_vector(signed(A) + signed(not B) + 1); --two's complement subtraction
        O <= sum;
    elsif(temp = "10") then
    else
        if(A = B) then
            EQ <= '1';
        else  
            EQ <= '0';
        end if;
    end if;
end process;
end behav;

register.vhdl
library ieee;
use ieee.std_logic_1164.all;

entity reg is
port(	I:	in std_logic_vector (7 downto 0) := "00000000";
		clk:	in std_logic;
		O:	out std_logic_vector(7 downto 0) := "00000000"
);
end reg;

architecture behav of reg is
begin
process(clk) is
begin
	if(clk='1' and clk'event) then
		O <= I;
	end if;
end process;
end behav;

registerFile.vhdl
library ieee;
use ieee.std_logic_1164.all;

entity registerFile is
port(	rs1:	in std_logic_vector (1 downto 0); -- for loading addresses: 00 = register 1, 01 = register 2, 10 = register 3, 11 = register 4
		rs2: in std_logic_vector (1 downto 0); -- for loading addresses
		clk:    in std_logic;
        ws:        in std_logic_vector(1 downto 0); -- write selects address: 00 = register 1, 01 = register 2, 10 = register 3, 11 = register 4
		wd:		in std_logic_vector(7 downto 0); -- write data
        we:		in std_logic; -- positive level triggering in problem 3
		rd1:		out std_logic_vector (7 downto 0); -- 0: don't do anything; 1: shift_reg is enabled
        rd2:		out std_logic_vector (7 downto 0) -- 0: don't do anything; 1: shift_reg is enabled
);
end registerFile;


architecture behav of registerFile is

component reg
port (	I:	in std_logic_vector (7 downto 0);
        clk:    in std_logic; 
        O:	out std_logic_vector(7 downto 0)
);
end component;

signal i1: std_logic_vector(7 downto 0) := "00000000";
signal i2: std_logic_vector(7 downto 0) := "00000000";
signal i3: std_logic_vector(7 downto 0) := "00000000";
signal i4: std_logic_vector(7 downto 0) := "00000000";
signal o1: std_logic_vector(7 downto 0);
signal o2: std_logic_vector(7 downto 0);
signal o3: std_logic_vector(7 downto 0);
signal o4: std_logic_vector(7 downto 0);
signal clockSig: std_logic;
begin

--  Component instantiation.
reg_1: reg port map ( I => i1, clk => clockSig, O => o1); --left 4 bits
reg_2: reg port map ( I => i2, clk => clockSig, O => o2); --right 4 bits
reg_3: reg port map ( I => i3, clk => clockSig, O => o3); --right 4 bits
reg_4: reg port map ( I => i4, clk => clockSig, O => o4); --right 4 bits

process(clk) is
begin
    if(clk='1' and clk'event) then
        if(rs1="00") then --rd1 should output register 1
        rd1 <= o1;

        elsif(rs1="01") then --rd1 should output register 2
        rd1 <= o2;
        
        elsif(rs1="10") then --rd1 should output register 3
        rd1 <= o3;
        
        else --rd1 should output register 1
        rd1 <= o4;
        
        end if;
        if(rs2="00") then --rd2 should output register 1
        rd2 <= o1;

        elsif(rs2="01") then --rd2 should output register 2
        rd2 <= o2;
        
        elsif(rs2="10") then --rd2 should output register 3
        rd2 <= o3;
        
        else --rd2 should output register 1
        rd2 <= o4;

        end if;
        if(we='1') then
            if(ws="00") then --set i2 to wd
                i1 <= wd;
                
            elsif(ws="01") then --set i2 to wd
               i2 <= wd;
                
            elsif(ws="10") then --set i3 to wd
                i3 <= wd;
                
            else --set i4 to wd
                i4 <= wd;

            end if;
        end if;
        clockSig <= clk;
    end if;
end process;

end behav;

calculator.vhdl
library ieee;
use ieee.std_logic_1164.all;
use IEEE.numeric_std.all;

entity calculator is 
    port( --opcode key: ADD = 00, SUB = 11, LOAD = 01, CMP/PRINT = 10
        I: in std_logic_vector(7 downto 0) := "00000000"; --format is: opcode (7 downto 6), rd (5 downto 4), rs (3 downto 2), rt (1 downto 0)
        clk: in std_logic
    );
end entity calculator;

architecture behavioral of calculator is
component alu is  --this is the alu need to add 1 because vhdl name
    port(	A:	in std_logic_vector (7 downto 0);
        B:	in std_logic_vector (7 downto 0);
		opField: in std_logic_vector (1 downto 0); --This corresponds to the opfield in the 8-bit ISA instruction
		O:	out std_logic_vector(7 downto 0);
        EQ: out std_logic
);
end component alu;

component registerFile is
    port(	rs1:	in std_logic_vector (1 downto 0); -- for loading addresses: 00 = register 1, 01 = register 2, 10 = register 3, 11 = register 4
		rs2: in std_logic_vector (1 downto 0); -- for loading addresses
		clk:    in std_logic;
        ws:        in std_logic_vector(1 downto 0); -- write selects address: 00 = register 1, 01 = register 2, 10 = register 3, 11 = register 4
		wd:		in std_logic_vector(7 downto 0); -- write data
        we:		in std_logic; -- positive level triggering in problem 3
		rd1:		out std_logic_vector (7 downto 0); -- 0: don't do anything; 1: shift_reg is enabled
        rd2:		out std_logic_vector (7 downto 0) -- 0: don't do anything; 1: shift_reg is enabled
);
end component registerFile;

signal regOut1, regOut2, RegWrite : std_logic_vector(7 downto 0) := "00000000";
signal branch, we_signal : std_logic :='0'; --write enable = 1 for all except branch/compare
signal regIn1, regIn2, ws_signal :std_logic_vector(1 downto 0);
signal aluOutput : std_logic_vector(7 downto 0) := "00000000";
signal rType : std_logic := '0'; --signifies whether it is add/subtract (1) or load (0)
signal immediateOutput : std_logic_vector(7 downto 0) := "00000000";
--signal ws_signal : std_logic_vector (1 downto 0) := "00";
begin  
    regFile : registerFile port map(rs1 => I(5 downto 4), rs2 => I(3 downto 2), clk => clk, ws => ws_signal, wd=>regWrite, we => we_signal,rd1 =>regOut1, rd2 =>regOut2  );
    alu1: alu port map(A => regOut1, B => regOut2, opField => I(7 downto 6), O => aluOutput, EQ => branch);
    we_signal <= (I(7) and I(6)) or (not I(7) and not I(6)) or (not I(7) and I(6)); --write enable for when add, sub, or load is called
    rType <= (I(7) and I(6)) or (not I(7) and not I(6)); --add or subtract makes it 1
    immediateOutput(3 downto 0) <= I(3 downto 0);
    with I(3) select immediateOutput(7 downto 4) <=
        "0000" when '0',
        "1111" when others;
    with rType select regWrite <=
        aluOutput when '1',
        immediateOutput when others;
    with rType select ws_signal <=
        I(5 downto 4) when '0',
        I(1 downto 0) when others;

        --PUT LOAD IN A PROCESS STATEMENT
    
    process(clk)
    begin
        report "Reg Output Value of ALU: " & integer'image(to_integer(signed(RegWrite)));
        --report "Reg Output Value of we_signal " & std_logic'image(we_signal);
    end process;


end architecture behavioral;

calculator_tb.vhdl
library ieee;
use ieee.std_logic_1164.all;

--  A testbench has no ports.
entity calculator_tb is
end calculator_tb;

architecture behav of calculator_tb is
--  Declaration of the component that will be instantiated.
component calculator
port(	I: in std_logic_vector(7 downto 0);
        clk: in std_logic
);
end component;
--  Specifies which entity is bound with the component.
signal i: std_logic_vector(7 downto 0);
signal clock: std_logic;
begin
--  Component instantiation.
calculator1 : calculator port map(I => I, clk => clock);

--  This process does the real job.
process
type pattern_type is record
--  The inputs of the shift_reg.
i: std_logic_vector(7 downto 0);
clock: std_logic;
end record;
--  The patterns to apply.
type pattern_array is array (natural range <>) of pattern_type;
constant patterns : pattern_array := -- Order goes: Input address rs1,rs2,ws ; input data rd1,rd2,wd ; we clk
(("00000000", '0'),
("01010111", '1'),
("00000000", '0'),
("01001000", '1'),
("00000000", '0'),
("00000110", '1'),
("00000000", '0'),
("01000000", '1')); --clock enable = 0, won't write to register
begin
--  Check each pattern.
for n in patterns'range loop
--  Set the inputs.
i <= patterns(n).i;
clock <= patterns(n).clock;

--  Wait for the results.
wait for 1 ns;
--  Check the outputs.
end loop;
assert false report "end of test" severity note;
--  Wait forever; this will finish the simulation.
wait;
end process;
end behav;

calculator.vcd
$date
  Thu May 20 15:19:22 2021
$end
$version
  GHDL v0
$end
$timescale
  1 fs
$end
$scope module standard $end
$upscope $end
$scope module std_logic_1164 $end
$upscope $end
$scope module numeric_std $end
$upscope $end
$scope module calculator_tb $end
$var reg 8 ! i[7:0] $end
$var reg 1 " clock $end
$scope module calculator1 $end
$var reg 8 # i[7:0] $end
$var reg 1 $ clk $end
$var reg 8 % regout1[7:0] $end
$var reg 8 & regout2[7:0] $end
$var reg 8 ' regwrite[7:0] $end
$var reg 1 ( branch $end
$var reg 1 ) we_signal $end
$var reg 2 * regin1[1:0] $end
$var reg 2 + regin2[1:0] $end
$var reg 2 , ws_signal[1:0] $end
$var reg 8 - aluoutput[7:0] $end
$var reg 1 . rtype $end
$var reg 8 / immediateoutput[7:0] $end
$scope module regfile $end
$var reg 2 0 rs1[1:0] $end
$var reg 2 1 rs2[1:0] $end
$var reg 1 2 clk $end
$var reg 2 3 ws[1:0] $end
$var reg 8 4 wd[7:0] $end
$var reg 1 5 we $end
$var reg 8 6 rd1[7:0] $end
$var reg 8 7 rd2[7:0] $end
$var reg 8 8 i1[7:0] $end
$var reg 8 9 i2[7:0] $end
$var reg 8 : i3[7:0] $end
$var reg 8 ; i4[7:0] $end
$var reg 8 < o1[7:0] $end
$var reg 8 = o2[7:0] $end
$var reg 8 > o3[7:0] $end
$var reg 8 ? o4[7:0] $end
$var reg 1 @ clocksig $end
$scope module reg_1 $end
$var reg 8 A i[7:0] $end
$var reg 1 B clk $end
$var reg 8 C o[7:0] $end
$upscope $end
$scope module reg_2 $end
$var reg 8 D i[7:0] $end
$var reg 1 E clk $end
$var reg 8 F o[7:0] $end
$upscope $end
$scope module reg_3 $end
$var reg 8 G i[7:0] $end
$var reg 1 H clk $end
$var reg 8 I o[7:0] $end
$upscope $end
$scope module reg_4 $end
$var reg 8 J i[7:0] $end
$var reg 1 K clk $end
$var reg 8 L o[7:0] $end
$upscope $end
$upscope $end
$scope module alu1 $end
$var reg 8 M a[7:0] $end
$var reg 8 N b[7:0] $end
$var reg 2 O opfield[1:0] $end
$var reg 8 P o[7:0] $end
$var reg 1 Q eq $end
$var reg 2 R temp[1:0] $end
$var reg 8 S sum[7:0] $end
$upscope $end
$upscope $end
$upscope $end
$enddefinitions $end
#0
b00000000 !
0"
b00000000 #
0$
b00000000 %
b00000000 &
b00000000 '
0(
1)
bUU *
bUU +
b00 ,
b00000000 -
1.
b00000000 /
b00 0
b00 1
02
b00 3
b00000000 4
15
b00000000 6
b00000000 7
b00000000 8
b00000000 9
b00000000 :
b00000000 ;
b00000000 <
b00000000 =
b00000000 >
b00000000 ?
0@
b00000000 A
0B
b00000000 C
b00000000 D
0E
b00000000 F
b00000000 G
0H
b00000000 I
b00000000 J
0K
b00000000 L
b00000000 M
b00000000 N
b00 O
b00000000 P
0Q
b00 R
b00000000 S
#1000000
b01010111 !
1"
b01010111 #
1$
b00000111 '
b01 ,
0.
b00000111 /
b01 0
b01 1
12
b01 3
b00000111 4
1@
1B
1E
1H
1K
b01 O
b10 R
#2000000
b00000000 !
0"
b00000000 #
0$
b00000000 '
b00 ,
1.
b00000000 /
b00 0
b00 1
02
b00 3
b00000000 4
0@
0B
0E
0H
0K
b00 O
b00 R
#3000000
b01001000 !
1"
b01001000 #
1$
b11111000 '
0.
b11111000 /
b10 1
12
b11111000 4
1@
1B
1E
1H
1K
b01 O
b10 R
#4000000
b00000000 !
0"
b00000000 #
0$
b00000000 '
1.
b00000000 /
b00 1
02
b00000000 4
0@
0B
0E
0H
0K
b00 O
b00 R
#5000000
b00000110 !
1"
b00000110 #
1$
b10 ,
b00000110 /
b01 1
12
b10 3
1@
1B
1E
1H
1K
#6000000
b00000000 !
0"
b00000000 #
0$
b00 ,
b00000000 /
b00 1
02
b00 3
0@
0B
0E
0H
0K
#7000000
b01000000 !
1"
b01000000 #
1$
0.
12
1@
1B
1E
1H
1K
b01 O
b10 R
