calculator_controller.vhdl
library ieee;
use ieee.std_logic_1164.all;
use IEEE.numeric_std.all;

entity calculator_controller is 
    port( --opcode key: calculator controller relies on opfield and alu eq output of main alu
        opCode, imm: in std_logic_vector(1 downto 0);
        equals: in std_logic;
        rType, printing, branchConfirm, writeEnable: out std_logic;
        regWriteSelector: out std_logic_vector (1 downto 0)
    );
end entity calculator_controller;

architecture behavioral of calculator_controller is
begin
    rType <= (opCode(1) and opCode(0)) or (not opCode(1) and not opCode(0));

    branchConfirm <= equals and (imm(1) xor imm(0));

    printing <= (opCode(1) and not opCode(0)) and (imm(1) and imm(0)); -- printing means opcode 10 and immediate 11

    writeEnable <= not(opCode(1) and not opCode(0)); --writeEnable = 1 for all except beq and print (opcode == 10)

    regWriteSelector <= ((opCode(1) and opCode(0)) or (not opCode(1) and not opCode(0))) & ((opCode(1) and not opCode(0)) and (imm(1) and imm(0))); --rType and printing
end architecture behavioral;

alu.vhdl
library ieee;
use ieee.std_logic_1164.all;
use IEEE.numeric_std.all;

entity alu is
port(	A:	in std_logic_vector (7 downto 0):= "00000000";
        B:	in std_logic_vector (7 downto 0):= "00000000";
		opField: in std_logic_vector (1 downto 0); --This corresponds to the opfield in the 8-bit ISA instruction
		O:	out std_logic_vector(7 downto 0) := "00000000";
        EQ: out std_logic
);
end alu;

architecture behav of alu is
signal temp: std_logic_vector(1 downto 0);
signal sum: std_logic_vector(7 downto 0);
begin
process(A, B, opField, temp, sum) is
begin
    temp(1) <= opField(1) xor opField(0);
    temp(0) <= (opField(1) and opField(0)) or (opField(1) and not opField(0));

    EQ <= '0';
	if(temp = "00") then
        sum <= std_logic_vector(signed(A) + signed(B));
        O <= sum;
    elsif(temp = "01") then
        sum <= std_logic_vector(signed(A) + signed(not B) + 1); --two's complement subtraction
        O <= sum;
    elsif(temp = "10") then
    else
        if(A = B) then
            EQ <= '1';
        else  
            EQ <= '0';
        end if;
    end if;
end process;
end behav;

register.vhdl
library ieee;
use ieee.std_logic_1164.all;

entity reg is
port(	I:	in std_logic_vector (7 downto 0);
		clk:	in std_logic;
		O:	out std_logic_vector(7 downto 0)
);
end reg;

architecture behav of reg is
begin
process(clk) is
begin
	if(clk='1' and clk'event) then
		O <= I;
	end if;
end process;
end behav;

registerFile.vhdl
library ieee;
use ieee.std_logic_1164.all;

entity registerFile is
port(	rs1:	in std_logic_vector (1 downto 0); -- for loading addresses: 00 = register 1, 01 = register 2, 10 = register 3, 11 = register 4
		rs2: in std_logic_vector (1 downto 0); -- for loading addresses
		clk:    in std_logic;
        ws:        in std_logic_vector(1 downto 0); -- write selects address: 00 = register 1, 01 = register 2, 10 = register 3, 11 = register 4
		wd:		in std_logic_vector(7 downto 0); -- write data
        we:		in std_logic; -- positive level triggering in problem 3
		rd1:		out std_logic_vector (7 downto 0) := "00000000"; -- 0: don't do anything; 1: shift_reg is enabled
        rd2:		out std_logic_vector (7 downto 0) := "00000000" -- 0: don't do anything; 1: shift_reg is enabled
);
end registerFile;


architecture behav of registerFile is

component reg
port (	I:	in std_logic_vector (7 downto 0) := "00000000";
        clk:    in std_logic; 
        O:	out std_logic_vector(7 downto 0) := "00000000"
);
end component;

signal i1: std_logic_vector(7 downto 0) := "00000000";
signal i2: std_logic_vector(7 downto 0) := "00000000";
signal i3: std_logic_vector(7 downto 0) := "00000000";
signal i4: std_logic_vector(7 downto 0) := "00000000";
signal o1: std_logic_vector(7 downto 0) := "00000000";
signal o2: std_logic_vector(7 downto 0) := "00000000";
signal o3: std_logic_vector(7 downto 0) := "00000000";
signal o4: std_logic_vector(7 downto 0) := "00000000";
signal weAndws : std_logic_vector(2 downto 0);
signal clk_sig1, clk_sig2, clk_sig3 : std_logic;
begin

--  Component instantiation.
reg_1: reg port map ( I => i1, clk => clk_sig3, O => o1); --left 4 bits
reg_2: reg port map ( I => i2, clk => clk_sig3, O => o2); --right 4 bits
reg_3: reg port map ( I => i3, clk => clk_sig3, O => o3); --right 4 bits
reg_4: reg port map ( I => i4, clk => clk_sig3, O => o4); --right 4 bits

weAndws <= we & ws;

with weAndws select
    i1 <=   wd when "100",
            o1 when others;

with weAndws select
i2 <=   wd when "101",
        o2 when others;     

with weAndws select
i3 <=   wd when "110",
        o3 when others;

with weAndws select
i4 <=   wd when "111",
    o4 when others;  

with rs1 select --combinational read of rs1
    rd1 <= o1 when "00",
           o2 when "01",
           o3 when "10",
           o4 when others;

with rs2 select --combinational read of rs2
    rd2 <= o1 when "00",
           o2 when "01",
           o3 when "10",
           o4 when others;

process(clk)
begin
    clk_sig1 <= clk;
end process;

process(clk_sig1)
begin
    clk_sig2 <= clk_sig1;
end process;

process(clk_sig2)
begin
    clk_sig3 <= clk_sig2;
end process;

end behav;

calculator.vhdl
library ieee;
use ieee.std_logic_1164.all;
use IEEE.numeric_std.all;

entity calculator is 
    port( --opcode key: ADD = 00, SUB = 11, LOAD = 01, CMP/PRINT = 10
        I: in std_logic_vector(7 downto 0) := "00000000"; --format is: opcode (7 downto 6), rs (5 downto 4), rt (3 downto 2), rd (1 downto 0) for rType, 
        clk: in std_logic                                 --opcode(7 downto 6), rd(5 downto 4), im (3 downto 0) for I-type
    );
end entity calculator;

architecture behavioral of calculator is
component alu is  --this is the alu need to add 1 because vhdl name
    port(	A:	in std_logic_vector (7 downto 0);
        B:	in std_logic_vector (7 downto 0);
		opField: in std_logic_vector (1 downto 0); --This corresponds to the opfield in the 8-bit ISA instruction
		O:	out std_logic_vector(7 downto 0);
        EQ: out std_logic
);
end component alu;

component reg is
    port(	I:	in std_logic_vector (7 downto 0) := "00000000";
            clk:	in std_logic;
            O:	out std_logic_vector(7 downto 0) := "00000000"
    );
end component reg;

component calculator_controller is
    port( --opcode key: calculator controller relies on opfield and alu eq output of main alu
        opCode, imm: in std_logic_vector(1 downto 0);
        equals: in std_logic;
        rType, printing, branchConfirm, writeEnable: out std_logic;
        regWriteSelector: out std_logic_vector (1 downto 0)
        );
end component;

component registerFile is
    port(	rs1:	in std_logic_vector (1 downto 0); -- for loading addresses: 00 = register 1, 01 = register 2, 10 = register 3, 11 = register 4
		rs2: in std_logic_vector (1 downto 0); -- for loading addresses
		clk:    in std_logic;
        ws:        in std_logic_vector(1 downto 0); -- write selects address: 00 = register 1, 01 = register 2, 10 = register 3, 11 = register 4
		wd:		in std_logic_vector(7 downto 0); -- write data
        we:		in std_logic; -- positive level triggering in problem 3
		rd1:		out std_logic_vector (7 downto 0); -- 0: don't do anything; 1: shift_reg is enabled
        rd2:		out std_logic_vector (7 downto 0) -- 0: don't do anything; 1: shift_reg is enabled
);
end component registerFile;


signal regFileInputA, regFileInputB, regDest: std_logic_vector(1 downto 0);
signal regWrite : std_logic_vector(7 downto 0);
signal writeEnable : std_logic;
signal regFileOutputA, regFileOutputB: std_logic_vector(7 downto 0);
signal aluInputA, aluInputB: std_logic_vector(7 downto 0);
signal aluOpField: std_logic_vector(1 downto 0);
signal aluOutput, aluOutputBuffer : std_logic_vector(7 downto 0);
signal aluBranchConfirm, aluBranchOutput: std_logic;
signal rType : std_logic; --signifies whether it is add/subtract (1) or load (0)
signal immExtend : std_logic_vector(7 downto 0); --immedate 0 or 1 padded
signal opCodeAndClk: std_logic_vector(2 downto 0);
signal clk_sig1, clk_sig2, clk_sig3, clk_sig4, clk_sig5, clk_sig6, clk_sig7, clk_sig8, clk_sig9 : std_logic := '0';
signal printOrBranch, printing : std_logic := '0';
signal regWriteSelector : std_logic_vector(1 downto 0);

--beq signals
signal beqRegisterInputA, beqRegisterInputB, beqRegisterSelect : std_logic_vector (1 downto 0);
signal beqRegisterOutputA, beqRegisterOutputB, beqRegisterWrite, beqRegisterDecremented : std_logic_vector(7 downto 0);
signal branchCounter : std_logic_vector(1 downto 0) := "00";
signal IBuffer : std_logic_vector(7 downto 0);

--signal ws_signal : std_logic_vector (1 downto 0) := "00";
begin  

    beqRegisterFile : registerFile port map(rs1 => "00", rs2 => "01", clk => clk_sig5, ws => "00", wd=>beqRegisterWrite, we => '1',rd1 =>beqRegisterOutputA, rd2 =>beqRegisterOutputB  );


    --mux selected by aluBranchConfirm (from controller) to choose what to set the beqRegister to
    with aluBranchconfirm select
        beqRegisterWrite <= "000000" & I(1 downto 0) when '1',
                            beqRegisterDecremented when others;

    --mux-implemented decrementer
    with beqRegisterOutputA select
        beqRegisterDecremented <=   std_logic_vector(unsigned(beqRegisterOutputA) - 1) when "00000010", --two's complement subtraction
                                    std_logic_vector(unsigned(beqRegisterOutputA) - 1) when "00000001", --two's complement subtraction
                                    "00000000" when others;
    
    --beq can skip either 1 or 2, if skipping a line set the input to "00000000"
    with beqRegisterOutputA(1 downto 0) select
        IBuffer <=  I when "00",
                    "00000000" when others;


    regFile : registerFile port map(rs1 => IBuffer(5 downto 4), rs2 => IBuffer(3 downto 2), clk => clk_sig9, ws => regDest, wd=>regWrite, we => writeEnable,rd1 =>regFileOutputA, rd2 =>regFileOutputB  );
    alu1: alu port map(A => regFileOutputA, B => regFileOutputB, opField => IBuffer(7 downto 6), O => aluOutput, EQ => aluBranchOutput);
    controller: calculator_controller port map(opCode => I(7 downto 6), imm => I(1 downto 0), equals => aluBranchOutput, rType => rType, printing => printing, branchConfirm => aluBranchConfirm, writeEnable => writeEnable, regWriteSelector => regWriteSelector);

    --controller changes the register being written to
    with rType select
        regDest <= IBuffer(1 downto 0) when '1', --add/sub has regDest at last 2 bits
                   IBuffer(5 downto 4) when others; --load is at 2 bits 2 to the left 
    
    --controller selects what to write to the register
    with regWriteSelector select
        regWrite <= aluOutput when "10", --add/sub gets regWrite from alu
                    immExtend when "00", --load gets regWrite from immediate field
                    regFileOutputA when others; --DO NOT CHANGE regWrite WHEN PRINTING = 1
    
    --sign extender
    with IBuffer(3) select
        immExtend <= "0000" & IBuffer(3 downto 0) when '0',
                     "1111" & IBuffer(3 downto 0) when others;

    process(clk)
    begin
        if(clk = '1' and clk'event and printing = '1') then --print
            if(beqRegisterOutputA(1 downto 0) = "00") then --if there are still lines left to skip, don't print
                report integer'image(to_integer(signed(RegWrite))); 
            end if;
        end if;
        clk_sig1 <= clk;
    end process;

    clk_sig2 <= clk_sig1; --need to match delta delays for clock and all the logic
    clk_sig3 <= clk_sig2;
    clk_sig4 <= clk_sig3;
    clk_sig5 <= clk_sig4;
    clk_sig6 <= clk_sig5;
    clk_sig7 <= clk_sig6;


    process(clk_sig7)
    begin
        if(beqRegisterOutputA(1 downto 0) = "00") then --if there are still lines left to skip, don't update the clock
            clk_sig8 <= clk_sig7;
        end if;
    end process;

    process(clk_sig8)
    begin
        if(clk_sig8 = '1' and clk_sig8'event) then
            --report "regWrite: " & integer'image(to_integer(signed(RegWrite))); --debugging for regWrite
        end if;
        clk_sig9 <= clk_sig8;
    end process;

end architecture behavioral;

calculator_tb.vhdl
library ieee;
use ieee.std_logic_1164.all;
use std.textio.all;

--  A testbench has no ports.
entity calculator_tb is
end calculator_tb;

architecture behav of calculator_tb is
--  Declaration of the component that will be instantiated.
component calculator
port(	I: in std_logic_vector(7 downto 0);
        clk: in std_logic
);
end component;
--  Specifies which entity is bound with the component.
signal I: std_logic_vector(7 downto 0);
signal clock: std_logic;
begin
--  Component instantiation.
calculator1 : calculator port map(I => I, clk => clock);

--  This process does the real job.
--The instructionFile located at instructions.txt contains the instructions:
--01000010   set reg1 to 2
--00000000   set reg1 to reg1 + reg1 (2 + 2 = 4)
--01110100   set reg4 to 4
--10000111   print reg1 (4)
--10000010   skip 2 lines if reg1 == reg4 (true) (4 = 4)
--10000011   print reg1 (4) (skipped)
--01000011   set reg1 to 3 (skipped)
--10001001   skip 1 line if reg1 == reg3 (false) (4 != 0)
--10010011   print reg2 (0)
--01101010   set reg3 to -6
--00101010   add reg3 to reg3 and put in reg3 (-6 + (-6) = -12)
--11001001   subtract reg3 from reg1 and put in reg1 (4 - (-12) = 16)
--10100011   print reg3 (-12)
--10010011   print reg1 (16)
process
      file instructionFile : text is in "instructions.txt"; --Instructions in text(ASCII) file.
      variable vector : bit_vector(7 downto 0);
      variable lineNum : line;
    begin
      while (not(endfile(instructionFile))) loop --Loop to the end of the text file.
        clock <= '0';
        readline(instructionFile, lineNum); --Read instruction from file
        read(lineNum, vector); --Change to bit vector
        I <= to_stdlogicvector(vector); --change bitvector to std_logic_vector
        wait for 1 ns;
        clock <= '1';
        wait for 1 ns;
      end loop;
      wait;
    end process;
    end behav;

calculator.vcd
$date
  Mon May 24 23:57:46 2021
$end
$version
  GHDL v0
$end
$timescale
  1 fs
$end
$scope module standard $end
$upscope $end
$scope module std_logic_1164 $end
$upscope $end
$scope module textio $end
$upscope $end
$scope module numeric_std $end
$upscope $end
$scope module calculator_tb $end
$var reg 8 ! i[7:0] $end
$var reg 1 " clock $end
$scope module calculator1 $end
$var reg 8 # i[7:0] $end
$var reg 1 $ clk $end
$var reg 2 % regfileinputa[1:0] $end
$var reg 2 & regfileinputb[1:0] $end
$var reg 2 ' regdest[1:0] $end
$var reg 8 ( regwrite[7:0] $end
$var reg 1 ) writeenable $end
$var reg 8 * regfileoutputa[7:0] $end
$var reg 8 + regfileoutputb[7:0] $end
$var reg 8 , aluinputa[7:0] $end
$var reg 8 - aluinputb[7:0] $end
$var reg 2 . aluopfield[1:0] $end
$var reg 8 / aluoutput[7:0] $end
$var reg 8 0 aluoutputbuffer[7:0] $end
$var reg 1 1 alubranchconfirm $end
$var reg 1 2 alubranchoutput $end
$var reg 1 3 rtype $end
$var reg 8 4 immextend[7:0] $end
$var reg 3 5 opcodeandclk[2:0] $end
$var reg 1 6 clk_sig1 $end
$var reg 1 7 clk_sig2 $end
$var reg 1 8 clk_sig3 $end
$var reg 1 9 clk_sig4 $end
$var reg 1 : clk_sig5 $end
$var reg 1 ; clk_sig6 $end
$var reg 1 < clk_sig7 $end
$var reg 1 = clk_sig8 $end
$var reg 1 > clk_sig9 $end
$var reg 1 ? printorbranch $end
$var reg 1 @ printing $end
$var reg 2 A regwriteselector[1:0] $end
$var reg 2 B beqregisterinputa[1:0] $end
$var reg 2 C beqregisterinputb[1:0] $end
$var reg 2 D beqregisterselect[1:0] $end
$var reg 8 E beqregisteroutputa[7:0] $end
$var reg 8 F beqregisteroutputb[7:0] $end
$var reg 8 G beqregisterwrite[7:0] $end
$var reg 8 H beqregisterdecremented[7:0] $end
$var reg 2 I branchcounter[1:0] $end
$var reg 8 J ibuffer[7:0] $end
$scope module beqregisterfile $end
$var reg 2 K rs1[1:0] $end
$var reg 2 L rs2[1:0] $end
$var reg 1 M clk $end
$var reg 2 N ws[1:0] $end
$var reg 8 O wd[7:0] $end
$var reg 1 P we $end
$var reg 8 Q rd1[7:0] $end
$var reg 8 R rd2[7:0] $end
$var reg 8 S i1[7:0] $end
$var reg 8 T i2[7:0] $end
$var reg 8 U i3[7:0] $end
$var reg 8 V i4[7:0] $end
$var reg 8 W o1[7:0] $end
$var reg 8 X o2[7:0] $end
$var reg 8 Y o3[7:0] $end
$var reg 8 Z o4[7:0] $end
$var reg 3 [ weandws[2:0] $end
$var reg 1 \ clk_sig1 $end
$var reg 1 ] clk_sig2 $end
$var reg 1 ^ clk_sig3 $end
$scope module reg_1 $end
$var reg 8 _ i[7:0] $end
$var reg 1 ` clk $end
$var reg 8 a o[7:0] $end
$upscope $end
$scope module reg_2 $end
$var reg 8 b i[7:0] $end
$var reg 1 c clk $end
$var reg 8 d o[7:0] $end
$upscope $end
$scope module reg_3 $end
$var reg 8 e i[7:0] $end
$var reg 1 f clk $end
$var reg 8 g o[7:0] $end
$upscope $end
$scope module reg_4 $end
$var reg 8 h i[7:0] $end
$var reg 1 i clk $end
$var reg 8 j o[7:0] $end
$upscope $end
$upscope $end
$scope module regfile $end
$var reg 2 k rs1[1:0] $end
$var reg 2 l rs2[1:0] $end
$var reg 1 m clk $end
$var reg 2 n ws[1:0] $end
$var reg 8 o wd[7:0] $end
$var reg 1 p we $end
$var reg 8 q rd1[7:0] $end
$var reg 8 r rd2[7:0] $end
$var reg 8 s i1[7:0] $end
$var reg 8 t i2[7:0] $end
$var reg 8 u i3[7:0] $end
$var reg 8 v i4[7:0] $end
$var reg 8 w o1[7:0] $end
$var reg 8 x o2[7:0] $end
$var reg 8 y o3[7:0] $end
$var reg 8 z o4[7:0] $end
$var reg 3 { weandws[2:0] $end
$var reg 1 | clk_sig1 $end
$var reg 1 } clk_sig2 $end
$var reg 1 !" clk_sig3 $end
$scope module reg_1 $end
$var reg 8 "" i[7:0] $end
$var reg 1 #" clk $end
$var reg 8 $" o[7:0] $end
$upscope $end
$scope module reg_2 $end
$var reg 8 %" i[7:0] $end
$var reg 1 &" clk $end
$var reg 8 '" o[7:0] $end
$upscope $end
$scope module reg_3 $end
$var reg 8 (" i[7:0] $end
$var reg 1 )" clk $end
$var reg 8 *" o[7:0] $end
$upscope $end
$scope module reg_4 $end
$var reg 8 +" i[7:0] $end
$var reg 1 ," clk $end
$var reg 8 -" o[7:0] $end
$upscope $end
$upscope $end
$scope module alu1 $end
$var reg 8 ." a[7:0] $end
$var reg 8 /" b[7:0] $end
$var reg 2 0" opfield[1:0] $end
$var reg 8 1" o[7:0] $end
$var reg 1 2" eq $end
$var reg 2 3" temp[1:0] $end
$var reg 8 4" sum[7:0] $end
$upscope $end
$scope module controller $end
$var reg 2 5" opcode[1:0] $end
$var reg 2 6" imm[1:0] $end
$var reg 1 7" equals $end
$var reg 1 8" rtype $end
$var reg 1 9" printing $end
$var reg 1 :" branchconfirm $end
$var reg 1 ;" writeenable $end
$var reg 2 <" regwriteselector[1:0] $end
$upscope $end
$upscope $end
$upscope $end
$enddefinitions $end
#0
b01000010 !
0"
b01000010 #
0$
bUU %
bUU &
b00 '
b00000010 (
1)
b00000000 *
b00000000 +
bUUUUUUUU ,
bUUUUUUUU -
bUU .
b00000000 /
bUUUUUUUU 0
01
02
03
b00000010 4
bUUU 5
06
07
08
09
0:
0;
0<
0=
0>
0?
0@
b00 A
bUU B
bUU C
bUU D
b00000000 E
b00000000 F
b00000000 G
b00000000 H
b00 I
b01000010 J
b00 K
b01 L
0M
b00 N
b00000000 O
1P
b00000000 Q
b00000000 R
b00000000 S
b00000000 T
b00000000 U
b00000000 V
b00000000 W
b00000000 X
b00000000 Y
b00000000 Z
b100 [
0\
0]
0^
b00000000 _
0`
b00000000 a
b00000000 b
0c
b00000000 d
b00000000 e
0f
b00000000 g
b00000000 h
0i
b00000000 j
b00 k
b00 l
0m
b00 n
b00000010 o
1p
b00000000 q
b00000000 r
b00000010 s
b00000000 t
b00000000 u
b00000000 v
b00000000 w
b00000000 x
b00000000 y
b00000000 z
b100 {
0|
0}
0!"
b00000010 ""
0#"
b00000000 $"
b00000000 %"
0&"
b00000000 '"
b00000000 ("
0)"
b00000000 *"
b00000000 +"
0,"
b00000000 -"
b00000000 ."
b00000000 /"
b01 0"
b00000000 1"
02"
b10 3"
bUUUUUUUU 4"
b01 5"
b10 6"
07"
08"
09"
0:"
1;"
b00 <"
#1000000
1"
1$
b00000010 *
b00000010 +
16
17
18
19
1:
1;
1<
1=
1>
1M
1\
1]
1^
1`
1c
1f
1i
1m
b00000010 q
b00000010 r
b00000010 w
1|
1}
1!"
1#"
b00000010 $"
1&"
1)"
1,"
b00000010 ."
b00000010 /"
#2000000
b00000000 !
0"
b00000000 #
0$
b00000100 (
b00000100 /
13
b00000000 4
06
07
08
09
0:
0;
0<
0=
0>
b10 A
b00000000 J
0M
0\
0]
0^
0`
0c
0f
0i
0m
b00000100 o
b00000100 s
0|
0}
0!"
b00000100 ""
0#"
0&"
0)"
0,"
b00 0"
b00000100 1"
b00 3"
b00000100 4"
b00 5"
b00 6"
18"
b10 <"
#3000000
1"
1$
b00001000 (
b00000100 *
b00000100 +
b00001000 /
16
17
18
19
1:
1;
1<
1=
1>
1M
1\
1]
1^
1`
1c
1f
1i
1m
b00001000 o
b00000100 q
b00000100 r
b00001000 s
b00000100 w
1|
1}
1!"
b00001000 ""
1#"
b00000100 $"
1&"
1)"
1,"
b00000100 ."
b00000100 /"
b00001000 1"
b00001000 4"
#4000000
b10000111 !
0"
b10000111 #
0$
b00000100 (
0)
b00000000 +
03
b00000111 4
06
07
08
09
0:
0;
0<
0=
0>
1@
b01 A
b10000111 J
0M
0\
0]
0^
0`
0c
0f
0i
b01 l
0m
b00000100 o
0p
b00000000 r
b00000100 s
b000 {
0|
0}
0!"
b00000100 ""
0#"
0&"
0)"
0,"
b00000000 /"
b10 0"
b11 3"
b10 5"
b11 6"
08"
19"
0;"
b01 <"
#5000000
1"
1$
16
17
18
19
1:
1;
1<
1=
1>
1M
1\
1]
1^
1`
1c
1f
1i
1m
1|
1}
1!"
1#"
1&"
1)"
1,"
#6000000
b10000010 !
0"
b10000010 #
0$
b00000010 (
b00000100 +
11
12
b00000010 4
06
07
08
09
0:
0;
0<
0=
0>
0@
b00 A
b00000010 G
b10000010 J
0M
b00000010 O
b00000010 S
0\
0]
0^
b00000010 _
0`
0c
0f
0i
b00 l
0m
b00000010 o
b00000100 r
0|
0}
0!"
0#"
0&"
0)"
0,"
b00000100 /"
12"
b10 6"
17"
09"
1:"
b00 <"
#7000000
1"
1$
b00000000 (
01
02
b00000000 4
16
17
18
19
1:
1;
1<
1=
1>
b00000010 E
b00000001 G
b00000001 H
b00000000 J
1M
b00000001 O
b00000010 Q
b00000001 S
b00000010 W
1\
1]
1^
b00000001 _
1`
b00000010 a
1c
1f
1i
1m
b00000000 o
1|
1}
1!"
1#"
1&"
1)"
1,"
b00 0"
02"
b00 3"
07"
0:"
#8000000
b10000011 !
0"
b10000011 #
0$
b00000100 (
06
07
08
09
0:
0;
0<
1@
b01 A
0M
0\
0]
0^
0`
0c
0f
0i
b00000100 o
b11 6"
19"
b01 <"
#9000000
1"
1$
16
17
18
19
1:
1;
1<
b00000001 E
b00000000 G
b00000000 H
1M
b00000000 O
b00000001 Q
b00000000 S
b00000001 W
1\
1]
1^
b00000000 _
1`
b00000001 a
1c
1f
1i
#10000000
b01000011 !
0"
b01000011 #
0$
b00000000 (
1)
06
07
08
09
0:
0;
0<
0@
b00 A
0M
0\
0]
0^
0`
0c
0f
0i
b00000000 o
1p
b00000000 s
b100 {
b00000000 ""
b01 5"
09"
1;"
b00 <"
#11000000
1"
1$
b00000011 (
b00000011 4
16
17
18
19
1:
1;
1<
b00000000 E
b01000011 J
1M
b00000000 Q
b00000000 W
1\
1]
1^
1`
b00000000 a
1c
1f
1i
b00000011 o
b00000011 s
b00000011 ""
b01 0"
b10 3"
#12000000
b10001001 !
0"
b10001001 #
0$
b11111001 (
0)
b00000000 +
b11111001 4
06
07
08
09
0:
0;
0<
0=
0>
b10001001 J
0M
0\
0]
0^
0`
0c
0f
0i
b10 l
0m
b11111001 o
0p
b00000000 r
b00000100 s
b000 {
0|
0}
0!"
b00000100 ""
0#"
0&"
0)"
0,"
b00000000 /"
b10 0"
b11 3"
b10 5"
b01 6"
0;"
#13000000
1"
1$
16
17
18
19
1:
1;
1<
1=
1>
1M
1\
1]
1^
1`
1c
1f
1i
1m
1|
1}
1!"
1#"
1&"
1)"
1,"
#14000000
b01011000 !
0"
b01011000 #
0$
b01 '
b11111000 (
1)
b00000000 *
b11111000 4
06
07
08
09
0:
0;
0<
0=
0>
b01011000 J
0M
0\
0]
0^
0`
0c
0f
0i
b01 k
0m
b01 n
b11111000 o
1p
b00000000 q
b00000100 s
b11111000 t
b101 {
0|
0}
0!"
b00000100 ""
0#"
b11111000 %"
0&"
0)"
0,"
b00000000 ."
b01 0"
b10 3"
b01 5"
b00 6"
1;"
#15000000
1"
1$
b11111000 *
16
17
18
19
1:
1;
1<
1=
1>
1M
1\
1]
1^
1`
1c
1f
1i
1m
b11111000 q
b11111000 x
1|
1}
1!"
1#"
1&"
b11111000 '"
1)"
1,"
b11111000 ."
