register.vhdl
library ieee;
use ieee.std_logic_1164.all;

entity reg is
port(	I:	in std_logic_vector (7 downto 0) := "00000000";
		clk:	in std_logic;
		O:	out std_logic_vector(7 downto 0) := "00000000";
		stable: out std_logic
);
end reg;

architecture behav of reg is
begin
process(clk) is
begin
	if(clk='1' and clk'event) then
		O <= I;
	end if;
	stable <= clk;
end process;
end behav;

registerFile.vhdl
library ieee;
use ieee.std_logic_1164.all;

entity registerFile is
port(	rs1:	in std_logic_vector (1 downto 0); -- for loading addresses: 00 = register 1, 01 = register 2, 10 = register 3, 11 = register 4
		rs2: in std_logic_vector (1 downto 0); -- for loading addresses
		clk:    in std_logic;
        ws:        in std_logic_vector(1 downto 0); -- write selects address: 00 = register 1, 01 = register 2, 10 = register 3, 11 = register 4
		wd:		in std_logic_vector(7 downto 0); -- write data
        we:		in std_logic; -- positive level triggering in problem 3
		rd1:		out std_logic_vector (7 downto 0) := "00000000"; -- 0: don't do anything; 1: shift_reg is enabled
        rd2:		out std_logic_vector (7 downto 0) := "00000000" -- 0: don't do anything; 1: shift_reg is enabled
);
end registerFile;


architecture behav of registerFile is

component reg
port (	I:	in std_logic_vector (7 downto 0) := "00000000";
        clk:    in std_logic; 
        O:	out std_logic_vector(7 downto 0) := "00000000";
        stable: out std_logic
);
end component;

signal i1: std_logic_vector(7 downto 0) := "00000000";
signal i2: std_logic_vector(7 downto 0) := "00000000";
signal i3: std_logic_vector(7 downto 0) := "00000000";
signal i4: std_logic_vector(7 downto 0) := "00000000";
signal o1: std_logic_vector(7 downto 0) := "00000000";
signal o2: std_logic_vector(7 downto 0) := "00000000";
signal o3: std_logic_vector(7 downto 0) := "00000000";
signal o4: std_logic_vector(7 downto 0) := "00000000";
signal clockSig: std_logic;
signal stabilizedWrite: std_logic := '0';
begin

--  Component instantiation.
reg_1: reg port map ( I => i1, clk => clockSig, O => o1, stable => stabilizedWrite); --left 4 bits
reg_2: reg port map ( I => i2, clk => clockSig, O => o2, stable => stabilizedWrite); --right 4 bits
reg_3: reg port map ( I => i3, clk => clockSig, O => o3, stable => stabilizedWrite); --right 4 bits
reg_4: reg port map ( I => i4, clk => clockSig, O => o4, stable => stabilizedWrite); --right 4 bits

process(clk) is
begin
    if(clk='1' and clk'event) then
        if(we='1') then
            if(ws="00") then --set i2 to wd
                i1 <= wd;
            elsif(ws="01") then --set i2 to wd
               i2 <= wd;
            elsif(ws="10") then --set i3 to wd
                i3 <= wd;
            else --set i4 to wd
                i4 <= wd;
            end if;
        end if;

    end if;
    clockSig <= clk;

end process;

WITH rs1 SELECT
rd1 <=
    o1 WHEN "00",
    o2 WHEN "01",
    o3 WHEN "10",
    o4 WHEN OTHERS;

WITH rs2 SELECT
rd2 <=
    o1 WHEN "00",
    o2 WHEN "01",
    o3 WHEN "10",
    o4 WHEN OTHERS;


end behav;

registerFile_tb.vhdl
library ieee;
use ieee.std_logic_1164.all;

--  A testbench has no ports.
entity registerFile_tb is
end registerFile_tb;

architecture behav of registerFile_tb is
--  Declaration of the component that will be instantiated.
component registerFile
port(	rs1:	in std_logic_vector (1 downto 0); -- for loading addresses: 00 = register 1, 01 = register 2, 10 = register 3, 11 = register 4
		rs2: in std_logic_vector (1 downto 0); -- for loading addresses
		clk:    in std_logic;
        ws:        in std_logic_vector(1 downto 0); -- write selects address: 00 = register 1, 01 = register 2, 10 = register 3, 11 = register 4
		wd:		in std_logic_vector(7 downto 0); -- write data
        we:		in std_logic; -- positive level triggering in problem 3
		rd1:		out std_logic_vector (7 downto 0); -- 0: don't do anything; 1: shift_reg is enabled
        rd2:		out std_logic_vector (7 downto 0) -- 0: don't do anything; 1: shift_reg is enabled
);
end component;
--  Specifies which entity is bound with the component.
signal rs1, rs2, ws : std_logic_vector(1 downto 0);
signal rd1, rd2, wd : std_logic_vector(7 downto 0);
signal we, clk : std_logic;
begin
--  Component instantiation.
registerFile1: registerFile port map (rs1 => rs1, rs2 => rs2, clk => clk, ws => ws, wd => wd, we => we, rd1 => rd1, rd2 => rd2);

--  This process does the real job.
process
type pattern_type is record
--  The inputs of the shift_reg.
rs1, rs2, ws : std_logic_vector(1 downto 0);
rd1, rd2, wd : std_logic_vector(7 downto 0);
we, clk : std_logic;
end record;
--  The patterns to apply.
type pattern_array is array (natural range <>) of pattern_type;
constant patterns : pattern_array := -- Order goes: Input address rs1,rs2,ws ; input data rd1,rd2,wd ; we clk
(("00", "01", "00", "00000000","00000000","11111111",'1', '0'), --test nothing happens on clock falling edge
("00", "01", "00", "00000001","00000000","00000001",'1', '1'), --ws selects register1 and writes 00000001 to it
("00", "01", "00", "00000001","00000000","00000001",'0', '0'), --test nothing happens on clock falling edge
("00", "01", "00", "00000001","00000000","11111111",'0', '1'), --clock enable = 0, won't write to register
("00", "01", "00", "00000001","00000000","00000000",'0', '0'), --test nothing happens on clock falling edge
("10", "00", "10", "11111111","00000001","11111111",'1', '1'), --change what registers are at rs1 and rs2 and simultaneously change what's at rs1
("00", "01", "00", "00000001","00000000","00000000",'0', '0'), --test nothing happens on clock falling edge HOWEVER YOU ARE ABLE TO CHANGE WHAT RD AND RS IS
("00", "01", "00", "00001001","00000000","00001001",'1', '1'), --ws selects register1 and writes 00000001 to it
("00", "01", "00", "00001001","00000000","00001001",'0', '1')); --clock enable = 0, won't write to register
begin
--  Check each pattern.
for n in patterns'range loop
--  Set the inputs.
rs1 <= patterns(n).rs1;
rs2 <= patterns(n).rs2;
ws <= patterns(n).ws;
wd <= patterns(n).wd;
clk <= patterns(n).clk;
we <= patterns(n).we;

--  Wait for the results.
wait for 1 ns;
--  Check the outputs.
assert rd1 = patterns(n).rd1
report "bad output value rd1" severity error;
assert rd2 = patterns(n).rd2
report "bad output value rd2" severity error;
end loop;
assert false report "end of test" severity note;
--  Wait forever; this will finish the simulation.
wait;
end process;
end behav;

registerFile_tb.vcd
$date
  Thu May  6 16:25:17 2021
$end
$version
  GHDL v0
$end
$timescale
  1 fs
$end
$scope module standard $end
$upscope $end
$scope module std_logic_1164 $end
$upscope $end
$scope module registerfile_tb $end
$var reg 2 ! rs1[1:0] $end
$var reg 2 " rs2[1:0] $end
$var reg 2 # ws[1:0] $end
$var reg 8 $ rd1[7:0] $end
$var reg 8 % rd2[7:0] $end
$var reg 8 & wd[7:0] $end
$var reg 1 ' we $end
$var reg 1 ( clk $end
$scope module registerfile1 $end
$var reg 2 ) rs1[1:0] $end
$var reg 2 * rs2[1:0] $end
$var reg 1 + clk $end
$var reg 2 , ws[1:0] $end
$var reg 8 - wd[7:0] $end
$var reg 1 . we $end
$var reg 8 / rd1[7:0] $end
$var reg 8 0 rd2[7:0] $end
$var reg 8 1 i1[7:0] $end
$var reg 8 2 i2[7:0] $end
$var reg 8 3 i3[7:0] $end
$var reg 8 4 i4[7:0] $end
$var reg 8 5 o1[7:0] $end
$var reg 8 6 o2[7:0] $end
$var reg 8 7 o3[7:0] $end
$var reg 8 8 o4[7:0] $end
$var reg 1 9 clocksig $end
$var reg 1 : stabilizedwrite $end
$scope module reg_1 $end
$var reg 8 ; i[7:0] $end
$var reg 1 < clk $end
$var reg 8 = o[7:0] $end
$var reg 1 > stable $end
$upscope $end
$scope module reg_2 $end
$var reg 8 ? i[7:0] $end
$var reg 1 @ clk $end
$var reg 8 A o[7:0] $end
$var reg 1 B stable $end
$upscope $end
$scope module reg_3 $end
$var reg 8 C i[7:0] $end
$var reg 1 D clk $end
$var reg 8 E o[7:0] $end
$var reg 1 F stable $end
$upscope $end
$scope module reg_4 $end
$var reg 8 G i[7:0] $end
$var reg 1 H clk $end
$var reg 8 I o[7:0] $end
$var reg 1 J stable $end
$upscope $end
$upscope $end
$upscope $end
$enddefinitions $end
#0
b00 !
b01 "
b00 #
b00000000 $
b00000000 %
b00000000 &
0'
0(
b00 )
b01 *
0+
b00 ,
b00000000 -
0.
b00000000 /
b00000000 0
b00000000 1
b00000000 2
b00000000 3
b00000000 4
b00000000 5
b00000000 6
b00000000 7
b00000000 8
09
0:
b00000000 ;
0<
b00000000 =
0>
b00000000 ?
0@
b00000000 A
0B
b00000000 C
0D
b00000000 E
0F
b00000000 G
0H
b00000000 I
0J
#1000000
b00000001 $
b00000001 &
1'
1(
1+
b00000001 -
1.
b00000001 /
b00000001 1
b00000001 5
19
1:
b00000001 ;
1<
b00000001 =
1>
1@
1B
1D
1F
1H
1J
#2000000
0'
0(
0+
0.
09
0:
0<
0>
0@
0B
0D
0F
0H
0J
#3000000
b00000000 &
1(
1+
b00000000 -
19
1:
1<
1>
1@
1B
1D
1F
1H
1J
#4000000
0(
0+
09
0:
0<
0>
0@
0B
0D
0F
0H
0J
#5000000
b10 !
b00 "
b10 #
b00000000 $
b00000001 %
1(
b10 )
b00 *
1+
b10 ,
b00000000 /
b00000001 0
19
1:
1<
1>
1@
1B
1D
1F
1H
1J
#6000000
b00 !
b01 "
b00 #
b00000001 $
b00000000 %
0(
b00 )
b01 *
0+
b00 ,
b00000001 /
b00000000 0
09
0:
0<
0>
0@
0B
0D
0F
0H
0J
#7000000
b00001001 $
b00001001 &
1'
1(
1+
b00001001 -
1.
b00001001 /
b00001001 1
b00001001 5
19
1:
b00001001 ;
1<
b00001001 =
1>
1@
1B
1D
1F
1H
1J
#8000000
b00000000 &
0'
b00000000 -
0.
